<workflow-app name="Ingest-Full-28" xmlns="uri:oozie:workflow:0.1">

 	<start to="AcquisitionAttributeType-Ingest-SPMM-Decision"/>


	<decision name="AcquisitionAttributeType-Ingest-SPMM-Decision">
    	<switch>
			<case to="AcquisitionAttributeType-Ingest-SPMM">${ wf:conf('job_SPMM_C1_OWNER_AcquisitionAttributeType_DoFull') eq 'true'}</case>
            <default to="AcquisitionVariant-Ingest-SPMM-Decision"/>
        </switch>
    </decision>

    <action name="AcquisitionAttributeType-Ingest-SPMM">
        <sqoop xmlns="uri:oozie:sqoop-action:0.2">
			<job-tracker>${jobTracker}</job-tracker>
            <name-node>${nameNode}</name-node>
			<prepare>
            	<delete path="${job_SPMM_C1_OWNER_AcquisitionAttributeType_DoFullTarget}" />
            </prepare>         	
            <arg>import</arg>
         	<arg>--connect</arg>
            <arg>jdbc:sqlserver://172.23.236.90:1433;database=SPMM_C1_OWNER</arg>
            <arg>--username</arg>
            <arg>usrSqoop</arg>
            <arg>--password</arg>
            <arg>AXm6Sn6#o</arg>
            <arg>--query</arg>
            <arg>SELECT AcquisitionAttributeTypeID,AcquisitionVariantID,AttributeTypeID,EntryOrder,Formula,IsExplicitStep, 2 as "org_id",  'SPMM' as "org_name"   FROM dbo.AcquisitionAttributeType WHERE ( $CONDITIONS ) </arg>
            <arg>--num-mappers</arg>
            <arg>1</arg>
            <arg>--target-dir</arg>
            <arg>${job_SPMM_C1_OWNER_AcquisitionAttributeType_DoFullTarget}</arg>
            <arg>--fields-terminated-by</arg>
            <arg>\t</arg>
            <arg>--direct</arg>
            <arg>--</arg>
            <arg>--schema</arg>
            <arg>dbo</arg>
            <arg>-validate</arg>
        </sqoop>
        <ok to="AcquisitionVariant-Ingest-SPMM-Decision"/>
        <error to="AcquisitionVariant-Ingest-SPMM-Decision"/>
    </action>

	<decision name="AcquisitionVariant-Ingest-SPMM-Decision">
    	<switch>
			<case to="AcquisitionVariant-Ingest-SPMM">${ wf:conf('job_SPMM_C1_OWNER_AcquisitionVariant_DoFull') eq 'true'}</case>
            <default to="ActionSubType-Ingest-SPMM-Decision"/>
        </switch>
    </decision>

    <action name="AcquisitionVariant-Ingest-SPMM">
        <sqoop xmlns="uri:oozie:sqoop-action:0.2">
			<job-tracker>${jobTracker}</job-tracker>
            <name-node>${nameNode}</name-node>
			<prepare>
            	<delete path="${job_SPMM_C1_OWNER_AcquisitionVariant_DoFullTarget}" />
            </prepare>         	
            <arg>import</arg>
         	<arg>--connect</arg>
            <arg>jdbc:sqlserver://172.23.236.90:1433;database=SPMM_C1_OWNER</arg>
            <arg>--username</arg>
            <arg>usrSqoop</arg>
            <arg>--password</arg>
            <arg>AXm6Sn6#o</arg>
            <arg>--query</arg>
            <arg>SELECT AcquisitionVariantID,AcquisitionID,MeasurementSetTagProfileID,PartInstanceTagProfileID,DefectTagProfileID,RfAcquisitionClassID,RfDataCollectionFreqID,DataCollectionPeriod,IsRetired,AcqPlan,VMTPID,CauseActionTPID,Variant,PartTypeID,RevisionNo,IsEdited,HeadAlias,CauseTagListID,ActionTagListID,IsMeasuredWhenProduced,IsInvPackCheck,IsEBATrigger, 2 as "org_id",  'SPMM' as "org_name"   FROM dbo.AcquisitionVariant WHERE ( $CONDITIONS ) </arg>
            <arg>--num-mappers</arg>
            <arg>1</arg>
            <arg>--target-dir</arg>
            <arg>${job_SPMM_C1_OWNER_AcquisitionVariant_DoFullTarget}</arg>
            <arg>--fields-terminated-by</arg>
            <arg>\t</arg>
            <arg>--direct</arg>
            <arg>--</arg>
            <arg>--schema</arg>
            <arg>dbo</arg>
            <arg>-validate</arg>
        </sqoop>
        <ok to="ActionSubType-Ingest-SPMM-Decision"/>
        <error to="ActionSubType-Ingest-SPMM-Decision"/>
    </action>

	<decision name="ActionSubType-Ingest-SPMM-Decision">
    	<switch>
			<case to="ActionSubType-Ingest-SPMM">${ wf:conf('job_SPMM_C1_OWNER_ActionSubType_DoFull') eq 'true'}</case>
            <default to="AssetExplosion-Ingest-SPMM-Decision"/>
        </switch>
    </decision>

    <action name="ActionSubType-Ingest-SPMM">
        <sqoop xmlns="uri:oozie:sqoop-action:0.2">
			<job-tracker>${jobTracker}</job-tracker>
            <name-node>${nameNode}</name-node>
			<prepare>
            	<delete path="${job_SPMM_C1_OWNER_ActionSubType_DoFullTarget}" />
            </prepare>         	
            <arg>import</arg>
         	<arg>--connect</arg>
            <arg>jdbc:sqlserver://172.23.236.90:1433;database=SPMM_C1_OWNER</arg>
            <arg>--username</arg>
            <arg>usrSqoop</arg>
            <arg>--password</arg>
            <arg>AXm6Sn6#o</arg>
            <arg>--query</arg>
            <arg>SELECT ActionSubTypeID,ActionSubType,ActionTypeID,Description,SubActionTypeCode,ReportOrder,Format,IsRetired, 2 as "org_id",  'SPMM' as "org_name"   FROM dbo.ActionSubType WHERE ( $CONDITIONS ) </arg>
            <arg>--num-mappers</arg>
            <arg>1</arg>
            <arg>--target-dir</arg>
            <arg>${job_SPMM_C1_OWNER_ActionSubType_DoFullTarget}</arg>
            <arg>--fields-terminated-by</arg>
            <arg>\t</arg>
            <arg>--direct</arg>
            <arg>--</arg>
            <arg>--schema</arg>
            <arg>dbo</arg>
            <arg>-validate</arg>
        </sqoop>
        <ok to="AssetExplosion-Ingest-SPMM-Decision"/>
        <error to="AssetExplosion-Ingest-SPMM-Decision"/>
    </action>

	<decision name="AssetExplosion-Ingest-SPMM-Decision">
    	<switch>
			<case to="AssetExplosion-Ingest-SPMM">${ wf:conf('job_SPMM_C1_OWNER_AssetExplosion_DoFull') eq 'true'}</case>
            <default to="AVDataEntryOptions-Ingest-SPMM-Decision"/>
        </switch>
    </decision>

    <action name="AssetExplosion-Ingest-SPMM">
        <sqoop xmlns="uri:oozie:sqoop-action:0.2">
			<job-tracker>${jobTracker}</job-tracker>
            <name-node>${nameNode}</name-node>
			<prepare>
            	<delete path="${job_SPMM_C1_OWNER_AssetExplosion_DoFullTarget}" />
            </prepare>         	
            <arg>import</arg>
         	<arg>--connect</arg>
            <arg>jdbc:sqlserver://172.23.236.90:1433;database=SPMM_C1_OWNER</arg>
            <arg>--username</arg>
            <arg>usrSqoop</arg>
            <arg>--password</arg>
            <arg>AXm6Sn6#o</arg>
            <arg>--query</arg>
            <arg>SELECT AssetID,ParentAssetID,SubAssetID,Lvl,SortOrder,Comments,AssetLevelID, 2 as "org_id",  'SPMM' as "org_name"   FROM dbo.AssetExplosion WHERE ( $CONDITIONS ) </arg>
            <arg>--num-mappers</arg>
            <arg>1</arg>
            <arg>--target-dir</arg>
            <arg>${job_SPMM_C1_OWNER_AssetExplosion_DoFullTarget}</arg>
            <arg>--fields-terminated-by</arg>
            <arg>\t</arg>
            <arg>--direct</arg>
            <arg>--</arg>
            <arg>--schema</arg>
            <arg>dbo</arg>
            <arg>-validate</arg>
        </sqoop>
        <ok to="AVDataEntryOptions-Ingest-SPMM-Decision"/>
        <error to="AVDataEntryOptions-Ingest-SPMM-Decision"/>
    </action>

	<decision name="AVDataEntryOptions-Ingest-SPMM-Decision">
    	<switch>
			<case to="AVDataEntryOptions-Ingest-SPMM">${ wf:conf('job_SPMM_C1_OWNER_AVDataEntryOptions_DoFull') eq 'true'}</case>
            <default to="Comments-Ingest-SPMM-Decision"/>
        </switch>
    </decision>

    <action name="AVDataEntryOptions-Ingest-SPMM">
        <sqoop xmlns="uri:oozie:sqoop-action:0.2">
			<job-tracker>${jobTracker}</job-tracker>
            <name-node>${nameNode}</name-node>
			<prepare>
            	<delete path="${job_SPMM_C1_OWNER_AVDataEntryOptions_DoFullTarget}" />
            </prepare>         	
            <arg>import</arg>
         	<arg>--connect</arg>
            <arg>jdbc:sqlserver://172.23.236.90:1433;database=SPMM_C1_OWNER</arg>
            <arg>--username</arg>
            <arg>usrSqoop</arg>
            <arg>--password</arg>
            <arg>AXm6Sn6#o</arg>
            <arg>--query</arg>
            <arg>SELECT AcquisitionVariantID,RfVarGridStyleID,IsPITCols,IsPISNoCol,RfAttrGridStyleID,IsStepGrid,IsAttrSkipStep,ShowAttrInfoTip,UseAttrImagePicker,AttrGridContextMenu,IsPISerial,AutoGenerateSerialNo,PITSampling,MSTSampling,VAInterlace,IsExplicitHS,SampleSizeMode,OnDataCommitGoTo,IsDisableOOSWarnings,StepEditPolicy,DisableKeyboardOverride,ChainToStopped,DisplayPlan,AttrPassFailDefault,VariableSaveMode,AttrCellClick, 2 as "org_id",  'SPMM' as "org_name"   FROM dbo.AVDataEntryOptions WHERE ( $CONDITIONS ) </arg>
            <arg>--num-mappers</arg>
            <arg>1</arg>
            <arg>--target-dir</arg>
            <arg>${job_SPMM_C1_OWNER_AVDataEntryOptions_DoFullTarget}</arg>
            <arg>--fields-terminated-by</arg>
            <arg>\t</arg>
            <arg>--direct</arg>
            <arg>--</arg>
            <arg>--schema</arg>
            <arg>dbo</arg>
            <arg>-validate</arg>
        </sqoop>
        <ok to="Comments-Ingest-SPMM-Decision"/>
        <error to="Comments-Ingest-SPMM-Decision"/>
    </action>

	<decision name="Comments-Ingest-SPMM-Decision">
    	<switch>
			<case to="Comments-Ingest-SPMM">${ wf:conf('job_SPMM_C1_OWNER_Comments_DoFull') eq 'true'}</case>
            <default to="CRN_AcquisitionVariableType-Ingest-SPMM-Decision"/>
        </switch>
    </decision>

    <action name="Comments-Ingest-SPMM">
        <sqoop xmlns="uri:oozie:sqoop-action:0.2">
			<job-tracker>${jobTracker}</job-tracker>
            <name-node>${nameNode}</name-node>
			<prepare>
            	<delete path="${job_SPMM_C1_OWNER_Comments_DoFullTarget}" />
            </prepare>         	
            <arg>import</arg>
         	<arg>--connect</arg>
            <arg>jdbc:sqlserver://172.23.236.90:1433;database=SPMM_C1_OWNER</arg>
            <arg>--username</arg>
            <arg>usrSqoop</arg>
            <arg>--password</arg>
            <arg>AXm6Sn6#o</arg>
            <arg>--query</arg>
            <arg>SELECT CommentsID,LoginID,DT,Subject,Comments, 2 as "org_id",  'SPMM' as "org_name"   FROM dbo.Comments WHERE ( $CONDITIONS ) </arg>
            <arg>--num-mappers</arg>
            <arg>1</arg>
            <arg>--target-dir</arg>
            <arg>${job_SPMM_C1_OWNER_Comments_DoFullTarget}</arg>
            <arg>--fields-terminated-by</arg>
            <arg>\t</arg>
            <arg>--direct</arg>
            <arg>--</arg>
            <arg>--schema</arg>
            <arg>dbo</arg>
            <arg>-validate</arg>
        </sqoop>
        <ok to="CRN_AcquisitionVariableType-Ingest-SPMM-Decision"/>
        <error to="CRN_AcquisitionVariableType-Ingest-SPMM-Decision"/>
    </action>

	<decision name="CRN_AcquisitionVariableType-Ingest-SPMM-Decision">
    	<switch>
			<case to="CRN_AcquisitionVariableType-Ingest-SPMM">${ wf:conf('job_SPMM_C1_OWNER_CRN_AcquisitionVariableType_DoFull') eq 'true'}</case>
            <default to="Document-Ingest-SPMM-Decision"/>
        </switch>
    </decision>

    <action name="CRN_AcquisitionVariableType-Ingest-SPMM">
        <sqoop xmlns="uri:oozie:sqoop-action:0.2">
			<job-tracker>${jobTracker}</job-tracker>
            <name-node>${nameNode}</name-node>
			<prepare>
            	<delete path="${job_SPMM_C1_OWNER_CRN_AcquisitionVariableType_DoFullTarget}" />
            </prepare>         	
            <arg>import</arg>
         	<arg>--connect</arg>
            <arg>jdbc:sqlserver://172.23.236.90:1433;database=SPMM_C1_OWNER</arg>
            <arg>--username</arg>
            <arg>usrSqoop</arg>
            <arg>--password</arg>
            <arg>AXm6Sn6#o</arg>
            <arg>--query</arg>
            <arg>SELECT AcquisitionVariableTypeID,JobCommentLength,RfTorqueDirectionID,RfCycleEndTimeID,ThresholdTorque,RfMeasurementTypeID,RfFrequencyResponseID,UnitID,AuditAngle,CrnAdapterID, 2 as "org_id",  'SPMM' as "org_name"   FROM dbo.CRN_AcquisitionVariableType WHERE ( $CONDITIONS ) </arg>
            <arg>--num-mappers</arg>
            <arg>1</arg>
            <arg>--target-dir</arg>
            <arg>${job_SPMM_C1_OWNER_CRN_AcquisitionVariableType_DoFullTarget}</arg>
            <arg>--fields-terminated-by</arg>
            <arg>\t</arg>
            <arg>--direct</arg>
            <arg>--</arg>
            <arg>--schema</arg>
            <arg>dbo</arg>
            <arg>-validate</arg>
        </sqoop>
        <ok to="Document-Ingest-SPMM-Decision"/>
        <error to="Document-Ingest-SPMM-Decision"/>
    </action>

	<decision name="Document-Ingest-SPMM-Decision">
    	<switch>
			<case to="Document-Ingest-SPMM">${ wf:conf('job_SPMM_C1_OWNER_Document_DoFull') eq 'true'}</case>
            <default to="FaultStatus-Ingest-SPMM-Decision"/>
        </switch>
    </decision>

    <action name="Document-Ingest-SPMM">
        <sqoop xmlns="uri:oozie:sqoop-action:0.2">
			<job-tracker>${jobTracker}</job-tracker>
            <name-node>${nameNode}</name-node>
			<prepare>
            	<delete path="${job_SPMM_C1_OWNER_Document_DoFullTarget}" />
            </prepare>         	
            <arg>import</arg>
         	<arg>--connect</arg>
            <arg>jdbc:sqlserver://172.23.236.90:1433;database=SPMM_C1_OWNER</arg>
            <arg>--username</arg>
            <arg>usrSqoop</arg>
            <arg>--password</arg>
            <arg>AXm6Sn6#o</arg>
            <arg>--query</arg>
            <arg>SELECT DocumentID,FileName,Description,MimeType,Attachment,UploadDT,LoginID,DocumentTypeID, 2 as "org_id",  'SPMM' as "org_name"   FROM dbo.Document WHERE ( $CONDITIONS ) </arg>
            <arg>--num-mappers</arg>
            <arg>1</arg>
            <arg>--target-dir</arg>
            <arg>${job_SPMM_C1_OWNER_Document_DoFullTarget}</arg>
            <arg>--fields-terminated-by</arg>
            <arg>\t</arg>
            <arg>--direct</arg>
            <arg>--</arg>
            <arg>--schema</arg>
            <arg>dbo</arg>
            <arg>-validate</arg>
        </sqoop>
        <ok to="FaultStatus-Ingest-SPMM-Decision"/>
        <error to="FaultStatus-Ingest-SPMM-Decision"/>
    </action>

	<decision name="FaultStatus-Ingest-SPMM-Decision">
    	<switch>
			<case to="FaultStatus-Ingest-SPMM">${ wf:conf('job_SPMM_C1_OWNER_FaultStatus_DoFull') eq 'true'}</case>
            <default to="InventoryUsage_-Ingest-SPMX-Decision"/>
        </switch>
    </decision>

    <action name="FaultStatus-Ingest-SPMM">
        <sqoop xmlns="uri:oozie:sqoop-action:0.2">
			<job-tracker>${jobTracker}</job-tracker>
            <name-node>${nameNode}</name-node>
			<prepare>
            	<delete path="${job_SPMM_C1_OWNER_FaultStatus_DoFullTarget}" />
            </prepare>         	
            <arg>import</arg>
         	<arg>--connect</arg>
            <arg>jdbc:sqlserver://172.23.236.90:1433;database=SPMM_C1_OWNER</arg>
            <arg>--username</arg>
            <arg>usrSqoop</arg>
            <arg>--password</arg>
            <arg>AXm6Sn6#o</arg>
            <arg>--query</arg>
            <arg>SELECT FaultStatusID,FaultStatus,Description,RfFaultStatusID, 2 as "org_id",  'SPMM' as "org_name"   FROM dbo.FaultStatus WHERE ( $CONDITIONS ) </arg>
            <arg>--num-mappers</arg>
            <arg>1</arg>
            <arg>--target-dir</arg>
            <arg>${job_SPMM_C1_OWNER_FaultStatus_DoFullTarget}</arg>
            <arg>--fields-terminated-by</arg>
            <arg>\t</arg>
            <arg>--direct</arg>
            <arg>--</arg>
            <arg>--schema</arg>
            <arg>dbo</arg>
            <arg>-validate</arg>
        </sqoop>
        <ok to="InventoryUsage_-Ingest-SPMX-Decision"/>
        <error to="InventoryUsage_-Ingest-SPMX-Decision"/>
    </action>

	<decision name="InventoryUsage_-Ingest-SPMX-Decision">
    	<switch>
			<case to="InventoryUsage_-Ingest-SPMX">${ wf:conf('job_MEXICALI_OWNER_InventoryUsage__DoFull') eq 'true'}</case>
            <default to="LineInfo_custom-Ingest-SPMM-Decision"/>
        </switch>
    </decision>

    <action name="InventoryUsage_-Ingest-SPMX">
        <sqoop xmlns="uri:oozie:sqoop-action:0.2">
			<job-tracker>${jobTracker}</job-tracker>
            <name-node>${nameNode}</name-node>
			<prepare>
            	<delete path="${job_MEXICALI_OWNER_InventoryUsage__DoFullTarget}" />
            </prepare>         	
            <arg>import</arg>
         	<arg>--connect</arg>
            <arg>jdbc:sqlserver://172.23.236.90:1433;database=MEXICALI_OWNER</arg>
            <arg>--username</arg>
            <arg>usrSqoop</arg>
            <arg>--password</arg>
            <arg>AXm6Sn6#o</arg>
            <arg>--query</arg>
            <arg>SELECT InventoryUsageID,StartUsingComments,StopUsingComments,StartLoginID,StopLoginID,OpenedStartDT,OpenedEndDT,SavedStartDT,SavedEndDT,OriginalLoginID,EditedInventoryUsageID,Reference1,Reference2,Reference3,Reference4,Reference5, 1 as "org_id",  'SPMX' as "org_name"   FROM dbo.InventoryUsage_ WHERE ( $CONDITIONS ) </arg>
            <arg>--num-mappers</arg>
            <arg>1</arg>
            <arg>--target-dir</arg>
            <arg>${job_MEXICALI_OWNER_InventoryUsage__DoFullTarget}</arg>
            <arg>--fields-terminated-by</arg>
            <arg>\t</arg>
            <arg>--direct</arg>
            <arg>--</arg>
            <arg>--schema</arg>
            <arg>dbo</arg>
            <arg>-validate</arg>
        </sqoop>
        <ok to="LineInfo_custom-Ingest-SPMM-Decision"/>
        <error to="LineInfo_custom-Ingest-SPMM-Decision"/>
    </action>

	<decision name="LineInfo_custom-Ingest-SPMM-Decision">
    	<switch>
			<case to="LineInfo_custom-Ingest-SPMM">${ wf:conf('job_SPMM_C1_OWNER_LineInfo_custom_DoFull') eq 'true'}</case>
            <default to="LkATATG-Ingest-SPMM-Decision"/>
        </switch>
    </decision>

    <action name="LineInfo_custom-Ingest-SPMM">
        <sqoop xmlns="uri:oozie:sqoop-action:0.2">
			<job-tracker>${jobTracker}</job-tracker>
            <name-node>${nameNode}</name-node>
			<prepare>
            	<delete path="${job_SPMM_C1_OWNER_LineInfo_custom_DoFullTarget}" />
            </prepare>         	
            <arg>import</arg>
         	<arg>--connect</arg>
            <arg>jdbc:sqlserver://172.23.236.90:1433;database=SPMM_C1_OWNER</arg>
            <arg>--username</arg>
            <arg>usrSqoop</arg>
            <arg>--password</arg>
            <arg>AXm6Sn6#o</arg>
            <arg>--query</arg>
            <arg>SELECT LineInfoID,CellsProduced, 2 as "org_id",  'SPMM' as "org_name"   FROM dbo.LineInfo_custom WHERE ( $CONDITIONS ) </arg>
            <arg>--num-mappers</arg>
            <arg>1</arg>
            <arg>--target-dir</arg>
            <arg>${job_SPMM_C1_OWNER_LineInfo_custom_DoFullTarget}</arg>
            <arg>--fields-terminated-by</arg>
            <arg>\t</arg>
            <arg>--direct</arg>
            <arg>--</arg>
            <arg>--schema</arg>
            <arg>dbo</arg>
            <arg>-validate</arg>
        </sqoop>
        <ok to="LkATATG-Ingest-SPMM-Decision"/>
        <error to="LkATATG-Ingest-SPMM-Decision"/>
    </action>

	<decision name="LkATATG-Ingest-SPMM-Decision">
    	<switch>
			<case to="LkATATG-Ingest-SPMM">${ wf:conf('job_SPMM_C1_OWNER_LkATATG_DoFull') eq 'true'}</case>
            <default to="LKCSetCDef-Ingest-SPMM-Decision"/>
        </switch>
    </decision>

    <action name="LkATATG-Ingest-SPMM">
        <sqoop xmlns="uri:oozie:sqoop-action:0.2">
			<job-tracker>${jobTracker}</job-tracker>
            <name-node>${nameNode}</name-node>
			<prepare>
            	<delete path="${job_SPMM_C1_OWNER_LkATATG_DoFullTarget}" />
            </prepare>         	
            <arg>import</arg>
         	<arg>--connect</arg>
            <arg>jdbc:sqlserver://172.23.236.90:1433;database=SPMM_C1_OWNER</arg>
            <arg>--username</arg>
            <arg>usrSqoop</arg>
            <arg>--password</arg>
            <arg>AXm6Sn6#o</arg>
            <arg>--query</arg>
            <arg>SELECT AttributeTypeGroupID,AttributeTypeID,LkATATGID, 2 as "org_id",  'SPMM' as "org_name"   FROM dbo.LkATATG WHERE ( $CONDITIONS ) </arg>
            <arg>--num-mappers</arg>
            <arg>1</arg>
            <arg>--target-dir</arg>
            <arg>${job_SPMM_C1_OWNER_LkATATG_DoFullTarget}</arg>
            <arg>--fields-terminated-by</arg>
            <arg>\t</arg>
            <arg>--direct</arg>
            <arg>--</arg>
            <arg>--schema</arg>
            <arg>dbo</arg>
            <arg>-validate</arg>
        </sqoop>
        <ok to="LKCSetCDef-Ingest-SPMM-Decision"/>
        <error to="LKCSetCDef-Ingest-SPMM-Decision"/>
    </action>

	<decision name="LKCSetCDef-Ingest-SPMM-Decision">
    	<switch>
			<case to="LKCSetCDef-Ingest-SPMM">${ wf:conf('job_SPMM_C1_OWNER_LKCSetCDef_DoFull') eq 'true'}</case>
            <default to="LkDocumentWIStep-Ingest-SPMM-Decision"/>
        </switch>
    </decision>

    <action name="LKCSetCDef-Ingest-SPMM">
        <sqoop xmlns="uri:oozie:sqoop-action:0.2">
			<job-tracker>${jobTracker}</job-tracker>
            <name-node>${nameNode}</name-node>
			<prepare>
            	<delete path="${job_SPMM_C1_OWNER_LKCSetCDef_DoFullTarget}" />
            </prepare>         	
            <arg>import</arg>
         	<arg>--connect</arg>
            <arg>jdbc:sqlserver://172.23.236.90:1433;database=SPMM_C1_OWNER</arg>
            <arg>--username</arg>
            <arg>usrSqoop</arg>
            <arg>--password</arg>
            <arg>AXm6Sn6#o</arg>
            <arg>--query</arg>
            <arg>SELECT SPCChartSetID,SPCChartDefID,Sequence,LkCSetCDefID, 2 as "org_id",  'SPMM' as "org_name"   FROM dbo.LKCSetCDef WHERE ( $CONDITIONS ) </arg>
            <arg>--num-mappers</arg>
            <arg>1</arg>
            <arg>--target-dir</arg>
            <arg>${job_SPMM_C1_OWNER_LKCSetCDef_DoFullTarget}</arg>
            <arg>--fields-terminated-by</arg>
            <arg>\t</arg>
            <arg>--direct</arg>
            <arg>--</arg>
            <arg>--schema</arg>
            <arg>dbo</arg>
            <arg>-validate</arg>
        </sqoop>
        <ok to="LkDocumentWIStep-Ingest-SPMM-Decision"/>
        <error to="LkDocumentWIStep-Ingest-SPMM-Decision"/>
    </action>

	<decision name="LkDocumentWIStep-Ingest-SPMM-Decision">
    	<switch>
			<case to="LkDocumentWIStep-Ingest-SPMM">${ wf:conf('job_SPMM_C1_OWNER_LkDocumentWIStep_DoFull') eq 'true'}</case>
            <default to="LkMachineStagePrinter-Ingest-SPMM-Decision"/>
        </switch>
    </decision>

    <action name="LkDocumentWIStep-Ingest-SPMM">
        <sqoop xmlns="uri:oozie:sqoop-action:0.2">
			<job-tracker>${jobTracker}</job-tracker>
            <name-node>${nameNode}</name-node>
			<prepare>
            	<delete path="${job_SPMM_C1_OWNER_LkDocumentWIStep_DoFullTarget}" />
            </prepare>         	
            <arg>import</arg>
         	<arg>--connect</arg>
            <arg>jdbc:sqlserver://172.23.236.90:1433;database=SPMM_C1_OWNER</arg>
            <arg>--username</arg>
            <arg>usrSqoop</arg>
            <arg>--password</arg>
            <arg>AXm6Sn6#o</arg>
            <arg>--query</arg>
            <arg>SELECT LkDocumentWIStepID,WorkInstructionStepID,DocumentID, 2 as "org_id",  'SPMM' as "org_name"   FROM dbo.LkDocumentWIStep WHERE ( $CONDITIONS ) </arg>
            <arg>--num-mappers</arg>
            <arg>1</arg>
            <arg>--target-dir</arg>
            <arg>${job_SPMM_C1_OWNER_LkDocumentWIStep_DoFullTarget}</arg>
            <arg>--fields-terminated-by</arg>
            <arg>\t</arg>
            <arg>--direct</arg>
            <arg>--</arg>
            <arg>--schema</arg>
            <arg>dbo</arg>
            <arg>-validate</arg>
        </sqoop>
        <ok to="LkMachineStagePrinter-Ingest-SPMM-Decision"/>
        <error to="LkMachineStagePrinter-Ingest-SPMM-Decision"/>
    </action>

	<decision name="LkMachineStagePrinter-Ingest-SPMM-Decision">
    	<switch>
			<case to="LkMachineStagePrinter-Ingest-SPMM">${ wf:conf('job_SPMM_C1_OWNER_LkMachineStagePrinter_DoFull') eq 'true'}</case>
            <default to="LkOpTPartTConsumed-Ingest-SPMM-Decision"/>
        </switch>
    </decision>

    <action name="LkMachineStagePrinter-Ingest-SPMM">
        <sqoop xmlns="uri:oozie:sqoop-action:0.2">
			<job-tracker>${jobTracker}</job-tracker>
            <name-node>${nameNode}</name-node>
			<prepare>
            	<delete path="${job_SPMM_C1_OWNER_LkMachineStagePrinter_DoFullTarget}" />
            </prepare>         	
            <arg>import</arg>
         	<arg>--connect</arg>
            <arg>jdbc:sqlserver://172.23.236.90:1433;database=SPMM_C1_OWNER</arg>
            <arg>--username</arg>
            <arg>usrSqoop</arg>
            <arg>--password</arg>
            <arg>AXm6Sn6#o</arg>
            <arg>--query</arg>
            <arg>SELECT LkMachineStagePrinterID,MachineStageID,PrinterID, 2 as "org_id",  'SPMM' as "org_name"   FROM dbo.LkMachineStagePrinter WHERE ( $CONDITIONS ) </arg>
            <arg>--num-mappers</arg>
            <arg>1</arg>
            <arg>--target-dir</arg>
            <arg>${job_SPMM_C1_OWNER_LkMachineStagePrinter_DoFullTarget}</arg>
            <arg>--fields-terminated-by</arg>
            <arg>\t</arg>
            <arg>--direct</arg>
            <arg>--</arg>
            <arg>--schema</arg>
            <arg>dbo</arg>
            <arg>-validate</arg>
        </sqoop>
        <ok to="LkOpTPartTConsumed-Ingest-SPMM-Decision"/>
        <error to="LkOpTPartTConsumed-Ingest-SPMM-Decision"/>
    </action>

	<decision name="LkOpTPartTConsumed-Ingest-SPMM-Decision">
    	<switch>
			<case to="LkOpTPartTConsumed-Ingest-SPMM">${ wf:conf('job_SPMM_C1_OWNER_LkOpTPartTConsumed_DoFull') eq 'true'}</case>
            <default to="LkRootCauseAction-Ingest-SPMM-Decision"/>
        </switch>
    </decision>

    <action name="LkOpTPartTConsumed-Ingest-SPMM">
        <sqoop xmlns="uri:oozie:sqoop-action:0.2">
			<job-tracker>${jobTracker}</job-tracker>
            <name-node>${nameNode}</name-node>
			<prepare>
            	<delete path="${job_SPMM_C1_OWNER_LkOpTPartTConsumed_DoFullTarget}" />
            </prepare>         	
            <arg>import</arg>
         	<arg>--connect</arg>
            <arg>jdbc:sqlserver://172.23.236.90:1433;database=SPMM_C1_OWNER</arg>
            <arg>--username</arg>
            <arg>usrSqoop</arg>
            <arg>--password</arg>
            <arg>AXm6Sn6#o</arg>
            <arg>--query</arg>
            <arg>SELECT PartTypeID,OperationTypeID,IsInventoryCarriedOver,LkOpTPartTConsumedID, 2 as "org_id",  'SPMM' as "org_name"   FROM dbo.LkOpTPartTConsumed WHERE ( $CONDITIONS ) </arg>
            <arg>--num-mappers</arg>
            <arg>1</arg>
            <arg>--target-dir</arg>
            <arg>${job_SPMM_C1_OWNER_LkOpTPartTConsumed_DoFullTarget}</arg>
            <arg>--fields-terminated-by</arg>
            <arg>\t</arg>
            <arg>--direct</arg>
            <arg>--</arg>
            <arg>--schema</arg>
            <arg>dbo</arg>
            <arg>-validate</arg>
        </sqoop>
        <ok to="LkRootCauseAction-Ingest-SPMM-Decision"/>
        <error to="LkRootCauseAction-Ingest-SPMM-Decision"/>
    </action>

	<decision name="LkRootCauseAction-Ingest-SPMM-Decision">
    	<switch>
			<case to="LkRootCauseAction-Ingest-SPMM">${ wf:conf('job_SPMM_C1_OWNER_LkRootCauseAction_DoFull') eq 'true'}</case>
            <default to="LkTSTC-Ingest-SPMM-Decision"/>
        </switch>
    </decision>

    <action name="LkRootCauseAction-Ingest-SPMM">
        <sqoop xmlns="uri:oozie:sqoop-action:0.2">
			<job-tracker>${jobTracker}</job-tracker>
            <name-node>${nameNode}</name-node>
			<prepare>
            	<delete path="${job_SPMM_C1_OWNER_LkRootCauseAction_DoFullTarget}" />
            </prepare>         	
            <arg>import</arg>
         	<arg>--connect</arg>
            <arg>jdbc:sqlserver://172.23.236.90:1433;database=SPMM_C1_OWNER</arg>
            <arg>--username</arg>
            <arg>usrSqoop</arg>
            <arg>--password</arg>
            <arg>AXm6Sn6#o</arg>
            <arg>--query</arg>
            <arg>SELECT LkRootCauseActionID,RootCauseID,ActionID, 2 as "org_id",  'SPMM' as "org_name"   FROM dbo.LkRootCauseAction WHERE ( $CONDITIONS ) </arg>
            <arg>--num-mappers</arg>
            <arg>1</arg>
            <arg>--target-dir</arg>
            <arg>${job_SPMM_C1_OWNER_LkRootCauseAction_DoFullTarget}</arg>
            <arg>--fields-terminated-by</arg>
            <arg>\t</arg>
            <arg>--direct</arg>
            <arg>--</arg>
            <arg>--schema</arg>
            <arg>dbo</arg>
            <arg>-validate</arg>
        </sqoop>
        <ok to="LkTSTC-Ingest-SPMM-Decision"/>
        <error to="LkTSTC-Ingest-SPMM-Decision"/>
    </action>

	<decision name="LkTSTC-Ingest-SPMM-Decision">
    	<switch>
			<case to="LkTSTC-Ingest-SPMM">${ wf:conf('job_SPMM_C1_OWNER_LkTSTC_DoFull') eq 'true'}</case>
            <default to="LkWIRMSetReq-Ingest-SPMM-Decision"/>
        </switch>
    </decision>

    <action name="LkTSTC-Ingest-SPMM">
        <sqoop xmlns="uri:oozie:sqoop-action:0.2">
			<job-tracker>${jobTracker}</job-tracker>
            <name-node>${nameNode}</name-node>
			<prepare>
            	<delete path="${job_SPMM_C1_OWNER_LkTSTC_DoFullTarget}" />
            </prepare>         	
            <arg>import</arg>
         	<arg>--connect</arg>
            <arg>jdbc:sqlserver://172.23.236.90:1433;database=SPMM_C1_OWNER</arg>
            <arg>--username</arg>
            <arg>usrSqoop</arg>
            <arg>--password</arg>
            <arg>AXm6Sn6#o</arg>
            <arg>--query</arg>
            <arg>SELECT ToolStateID,ToolCavityID,RfToolCavityStatusID,ToolCavityStateReasonID,IsCavityChangeState,LkTSTCID, 2 as "org_id",  'SPMM' as "org_name"   FROM dbo.LkTSTC WHERE ( $CONDITIONS ) </arg>
            <arg>--num-mappers</arg>
            <arg>1</arg>
            <arg>--target-dir</arg>
            <arg>${job_SPMM_C1_OWNER_LkTSTC_DoFullTarget}</arg>
            <arg>--fields-terminated-by</arg>
            <arg>\t</arg>
            <arg>--direct</arg>
            <arg>--</arg>
            <arg>--schema</arg>
            <arg>dbo</arg>
            <arg>-validate</arg>
        </sqoop>
        <ok to="LkWIRMSetReq-Ingest-SPMM-Decision"/>
        <error to="LkWIRMSetReq-Ingest-SPMM-Decision"/>
    </action>

	<decision name="LkWIRMSetReq-Ingest-SPMM-Decision">
    	<switch>
			<case to="LkWIRMSetReq-Ingest-SPMM">${ wf:conf('job_SPMM_C1_OWNER_LkWIRMSetReq_DoFull') eq 'true'}</case>
            <default to="MachineStageType-Ingest-SPMM-Decision"/>
        </switch>
    </decision>

    <action name="LkWIRMSetReq-Ingest-SPMM">
        <sqoop xmlns="uri:oozie:sqoop-action:0.2">
			<job-tracker>${jobTracker}</job-tracker>
            <name-node>${nameNode}</name-node>
			<prepare>
            	<delete path="${job_SPMM_C1_OWNER_LkWIRMSetReq_DoFullTarget}" />
            </prepare>         	
            <arg>import</arg>
         	<arg>--connect</arg>
            <arg>jdbc:sqlserver://172.23.236.90:1433;database=SPMM_C1_OWNER</arg>
            <arg>--username</arg>
            <arg>usrSqoop</arg>
            <arg>--password</arg>
            <arg>AXm6Sn6#o</arg>
            <arg>--query</arg>
            <arg>SELECT LkWIRMSetReqID,WorkInstructionResultID,MeasurementSetRequiredID, 2 as "org_id",  'SPMM' as "org_name"   FROM dbo.LkWIRMSetReq WHERE ( $CONDITIONS ) </arg>
            <arg>--num-mappers</arg>
            <arg>1</arg>
            <arg>--target-dir</arg>
            <arg>${job_SPMM_C1_OWNER_LkWIRMSetReq_DoFullTarget}</arg>
            <arg>--fields-terminated-by</arg>
            <arg>\t</arg>
            <arg>--direct</arg>
            <arg>--</arg>
            <arg>--schema</arg>
            <arg>dbo</arg>
            <arg>-validate</arg>
        </sqoop>
        <ok to="MachineStageType-Ingest-SPMM-Decision"/>
        <error to="MachineStageType-Ingest-SPMM-Decision"/>
    </action>

	<decision name="MachineStageType-Ingest-SPMM-Decision">
    	<switch>
			<case to="MachineStageType-Ingest-SPMM">${ wf:conf('job_SPMM_C1_OWNER_MachineStageType_DoFull') eq 'true'}</case>
            <default to="MaintenancePartPlanned-Ingest-SPMM-Decision"/>
        </switch>
    </decision>

    <action name="MachineStageType-Ingest-SPMM">
        <sqoop xmlns="uri:oozie:sqoop-action:0.2">
			<job-tracker>${jobTracker}</job-tracker>
            <name-node>${nameNode}</name-node>
			<prepare>
            	<delete path="${job_SPMM_C1_OWNER_MachineStageType_DoFullTarget}" />
            </prepare>         	
            <arg>import</arg>
         	<arg>--connect</arg>
            <arg>jdbc:sqlserver://172.23.236.90:1433;database=SPMM_C1_OWNER</arg>
            <arg>--username</arg>
            <arg>usrSqoop</arg>
            <arg>--password</arg>
            <arg>AXm6Sn6#o</arg>
            <arg>--query</arg>
            <arg>SELECT MachineStageTypeID,Name,Description,MachineStageTypeCode, 2 as "org_id",  'SPMM' as "org_name"   FROM dbo.MachineStageType WHERE ( $CONDITIONS ) </arg>
            <arg>--num-mappers</arg>
            <arg>1</arg>
            <arg>--target-dir</arg>
            <arg>${job_SPMM_C1_OWNER_MachineStageType_DoFullTarget}</arg>
            <arg>--fields-terminated-by</arg>
            <arg>\t</arg>
            <arg>--direct</arg>
            <arg>--</arg>
            <arg>--schema</arg>
            <arg>dbo</arg>
            <arg>-validate</arg>
        </sqoop>
        <ok to="MaintenancePartPlanned-Ingest-SPMM-Decision"/>
        <error to="MaintenancePartPlanned-Ingest-SPMM-Decision"/>
    </action>

	<decision name="MaintenancePartPlanned-Ingest-SPMM-Decision">
    	<switch>
			<case to="MaintenancePartPlanned-Ingest-SPMM">${ wf:conf('job_SPMM_C1_OWNER_MaintenancePartPlanned_DoFull') eq 'true'}</case>
            <default to="MaintenanceProcedureStep-Ingest-SPMM-Decision"/>
        </switch>
    </decision>

    <action name="MaintenancePartPlanned-Ingest-SPMM">
        <sqoop xmlns="uri:oozie:sqoop-action:0.2">
			<job-tracker>${jobTracker}</job-tracker>
            <name-node>${nameNode}</name-node>
			<prepare>
            	<delete path="${job_SPMM_C1_OWNER_MaintenancePartPlanned_DoFullTarget}" />
            </prepare>         	
            <arg>import</arg>
         	<arg>--connect</arg>
            <arg>jdbc:sqlserver://172.23.236.90:1433;database=SPMM_C1_OWNER</arg>
            <arg>--username</arg>
            <arg>usrSqoop</arg>
            <arg>--password</arg>
            <arg>AXm6Sn6#o</arg>
            <arg>--query</arg>
            <arg>SELECT MaintenancePartPlannedID,MaintenanceProcedureStepID,PartID,PlannedCost,IsOptional,Quantity,UnitID, 2 as "org_id",  'SPMM' as "org_name"   FROM dbo.MaintenancePartPlanned WHERE ( $CONDITIONS ) </arg>
            <arg>--num-mappers</arg>
            <arg>1</arg>
            <arg>--target-dir</arg>
            <arg>${job_SPMM_C1_OWNER_MaintenancePartPlanned_DoFullTarget}</arg>
            <arg>--fields-terminated-by</arg>
            <arg>\t</arg>
            <arg>--direct</arg>
            <arg>--</arg>
            <arg>--schema</arg>
            <arg>dbo</arg>
            <arg>-validate</arg>
        </sqoop>
        <ok to="MaintenanceProcedureStep-Ingest-SPMM-Decision"/>
        <error to="MaintenanceProcedureStep-Ingest-SPMM-Decision"/>
    </action>

	<decision name="MaintenanceProcedureStep-Ingest-SPMM-Decision">
    	<switch>
			<case to="MaintenanceProcedureStep-Ingest-SPMM">${ wf:conf('job_SPMM_C1_OWNER_MaintenanceProcedureStep_DoFull') eq 'true'}</case>
            <default to="MeasurementSet-Ingest-SPMM-Decision"/>
        </switch>
    </decision>

    <action name="MaintenanceProcedureStep-Ingest-SPMM">
        <sqoop xmlns="uri:oozie:sqoop-action:0.2">
			<job-tracker>${jobTracker}</job-tracker>
            <name-node>${nameNode}</name-node>
			<prepare>
            	<delete path="${job_SPMM_C1_OWNER_MaintenanceProcedureStep_DoFullTarget}" />
            </prepare>         	
            <arg>import</arg>
         	<arg>--connect</arg>
            <arg>jdbc:sqlserver://172.23.236.90:1433;database=SPMM_C1_OWNER</arg>
            <arg>--username</arg>
            <arg>usrSqoop</arg>
            <arg>--password</arg>
            <arg>AXm6Sn6#o</arg>
            <arg>--query</arg>
            <arg>SELECT MaintenanceProcedureStepID,MaintenanceProcedureStep,MaintenanceProcedureRevisionID,StepOrder,SubPartID,Component,RfMaintenanceCheckTypeID,RfSpecialActionTypeID,Test,USL,LSL,PersonnelGroupID,SupplierID,Nom,Units,DecPlaces, 2 as "org_id",  'SPMM' as "org_name"   FROM dbo.MaintenanceProcedureStep WHERE ( $CONDITIONS ) </arg>
            <arg>--num-mappers</arg>
            <arg>1</arg>
            <arg>--target-dir</arg>
            <arg>${job_SPMM_C1_OWNER_MaintenanceProcedureStep_DoFullTarget}</arg>
            <arg>--fields-terminated-by</arg>
            <arg>\t</arg>
            <arg>--direct</arg>
            <arg>--</arg>
            <arg>--schema</arg>
            <arg>dbo</arg>
            <arg>-validate</arg>
        </sqoop>
        <ok to="MeasurementSet-Ingest-SPMM-Decision"/>
        <error to="MeasurementSet-Ingest-SPMM-Decision"/>
    </action>

	<decision name="MeasurementSet-Ingest-SPMM-Decision">
    	<switch>
			<case to="MeasurementSet-Ingest-SPMM">${ wf:conf('job_SPMM_C1_OWNER_MeasurementSet_DoFull') eq 'true'}</case>
            <default to="OPCClient-Ingest-SPMM-Decision"/>
        </switch>
    </decision>

    <action name="MeasurementSet-Ingest-SPMM">
        <sqoop xmlns="uri:oozie:sqoop-action:0.2">
			<job-tracker>${jobTracker}</job-tracker>
            <name-node>${nameNode}</name-node>
			<prepare>
            	<delete path="${job_SPMM_C1_OWNER_MeasurementSet_DoFullTarget}" />
            </prepare>         	
            <arg>import</arg>
         	<arg>--connect</arg>
            <arg>jdbc:sqlserver://172.23.236.90:1433;database=SPMM_C1_OWNER</arg>
            <arg>--username</arg>
            <arg>usrSqoop</arg>
            <arg>--password</arg>
            <arg>AXm6Sn6#o</arg>
            <arg>--query</arg>
            <arg>SELECT MeasurementSetID,ActualAttrSampleSize,AcquisitionContextID,IsEdited,DT,AcquisitionID,MachineStageID,RfAcquisitionClassID,RevisionNo,PartID,JobID,ResumeStep,InventoryPackID, 2 as "org_id",  'SPMM' as "org_name"   FROM dbo.MeasurementSet WHERE ( $CONDITIONS ) </arg>
            <arg>--num-mappers</arg>
            <arg>1</arg>
            <arg>--target-dir</arg>
            <arg>${job_SPMM_C1_OWNER_MeasurementSet_DoFullTarget}</arg>
            <arg>--fields-terminated-by</arg>
            <arg>\t</arg>
            <arg>--direct</arg>
            <arg>--</arg>
            <arg>--schema</arg>
            <arg>dbo</arg>
            <arg>-validate</arg>
        </sqoop>
        <ok to="OPCClient-Ingest-SPMM-Decision"/>
        <error to="OPCClient-Ingest-SPMM-Decision"/>
    </action>

	<decision name="OPCClient-Ingest-SPMM-Decision">
    	<switch>
			<case to="OPCClient-Ingest-SPMM">${ wf:conf('job_SPMM_C1_OWNER_OPCClient_DoFull') eq 'true'}</case>
            <default to="OPCItemHistory-Ingest-SPMM-Decision"/>
        </switch>
    </decision>

    <action name="OPCClient-Ingest-SPMM">
        <sqoop xmlns="uri:oozie:sqoop-action:0.2">
			<job-tracker>${jobTracker}</job-tracker>
            <name-node>${nameNode}</name-node>
			<prepare>
            	<delete path="${job_SPMM_C1_OWNER_OPCClient_DoFullTarget}" />
            </prepare>         	
            <arg>import</arg>
         	<arg>--connect</arg>
            <arg>jdbc:sqlserver://172.23.236.90:1433;database=SPMM_C1_OWNER</arg>
            <arg>--username</arg>
            <arg>usrSqoop</arg>
            <arg>--password</arg>
            <arg>AXm6Sn6#o</arg>
            <arg>--query</arg>
            <arg>SELECT OPCClientID,OPCClient,ComputerID,ModifiedDT,LastUpdateDT, 2 as "org_id",  'SPMM' as "org_name"   FROM dbo.OPCClient WHERE ( $CONDITIONS ) </arg>
            <arg>--num-mappers</arg>
            <arg>1</arg>
            <arg>--target-dir</arg>
            <arg>${job_SPMM_C1_OWNER_OPCClient_DoFullTarget}</arg>
            <arg>--fields-terminated-by</arg>
            <arg>\t</arg>
            <arg>--direct</arg>
            <arg>--</arg>
            <arg>--schema</arg>
            <arg>dbo</arg>
            <arg>-validate</arg>
        </sqoop>
        <ok to="OPCItemHistory-Ingest-SPMM-Decision"/>
        <error to="OPCItemHistory-Ingest-SPMM-Decision"/>
    </action>

	<decision name="OPCItemHistory-Ingest-SPMM-Decision">
    	<switch>
			<case to="OPCItemHistory-Ingest-SPMM">${ wf:conf('job_SPMM_C1_OWNER_OPCItemHistory_DoFull') eq 'true'}</case>
            <default to="OPCText-Ingest-SPMM-Decision"/>
        </switch>
    </decision>

    <action name="OPCItemHistory-Ingest-SPMM">
        <sqoop xmlns="uri:oozie:sqoop-action:0.2">
			<job-tracker>${jobTracker}</job-tracker>
            <name-node>${nameNode}</name-node>
			<prepare>
            	<delete path="${job_SPMM_C1_OWNER_OPCItemHistory_DoFullTarget}" />
            </prepare>         	
            <arg>import</arg>
         	<arg>--connect</arg>
            <arg>jdbc:sqlserver://172.23.236.90:1433;database=SPMM_C1_OWNER</arg>
            <arg>--username</arg>
            <arg>usrSqoop</arg>
            <arg>--password</arg>
            <arg>AXm6Sn6#o</arg>
            <arg>--query</arg>
            <arg>SELECT OPCItemHistoryID,OPCItemID,UpdatedDT,RawValue,Value,Quality,CommittedDT, 2 as "org_id",  'SPMM' as "org_name"   FROM dbo.OPCItemHistory WHERE ( $CONDITIONS ) </arg>
            <arg>--num-mappers</arg>
            <arg>1</arg>
            <arg>--target-dir</arg>
            <arg>${job_SPMM_C1_OWNER_OPCItemHistory_DoFullTarget}</arg>
            <arg>--fields-terminated-by</arg>
            <arg>\t</arg>
            <arg>--direct</arg>
            <arg>--</arg>
            <arg>--schema</arg>
            <arg>dbo</arg>
            <arg>-validate</arg>
        </sqoop>
        <ok to="OPCText-Ingest-SPMM-Decision"/>
        <error to="OPCText-Ingest-SPMM-Decision"/>
    </action>

	<decision name="OPCText-Ingest-SPMM-Decision">
    	<switch>
			<case to="OPCText-Ingest-SPMM">${ wf:conf('job_SPMM_C1_OWNER_OPCText_DoFull') eq 'true'}</case>
            <default to="PartType-Ingest-SPMM-Decision"/>
        </switch>
    </decision>

    <action name="OPCText-Ingest-SPMM">
        <sqoop xmlns="uri:oozie:sqoop-action:0.2">
			<job-tracker>${jobTracker}</job-tracker>
            <name-node>${nameNode}</name-node>
			<prepare>
            	<delete path="${job_SPMM_C1_OWNER_OPCText_DoFullTarget}" />
            </prepare>         	
            <arg>import</arg>
         	<arg>--connect</arg>
            <arg>jdbc:sqlserver://172.23.236.90:1433;database=SPMM_C1_OWNER</arg>
            <arg>--username</arg>
            <arg>usrSqoop</arg>
            <arg>--password</arg>
            <arg>AXm6Sn6#o</arg>
            <arg>--query</arg>
            <arg>SELECT OPCTextID,OPCItemID,Description,ModifiedDT,LoginID, 2 as "org_id",  'SPMM' as "org_name"   FROM dbo.OPCText WHERE ( $CONDITIONS ) </arg>
            <arg>--num-mappers</arg>
            <arg>1</arg>
            <arg>--target-dir</arg>
            <arg>${job_SPMM_C1_OWNER_OPCText_DoFullTarget}</arg>
            <arg>--fields-terminated-by</arg>
            <arg>\t</arg>
            <arg>--direct</arg>
            <arg>--</arg>
            <arg>--schema</arg>
            <arg>dbo</arg>
            <arg>-validate</arg>
        </sqoop>
        <ok to="PartType-Ingest-SPMM-Decision"/>
        <error to="PartType-Ingest-SPMM-Decision"/>
    </action>

	<decision name="PartType-Ingest-SPMM-Decision">
    	<switch>
			<case to="PartType-Ingest-SPMM">${ wf:conf('job_SPMM_C1_OWNER_PartType_DoFull') eq 'true'}</case>
            <default to="ProductType-Ingest-SPMM-Decision"/>
        </switch>
    </decision>

    <action name="PartType-Ingest-SPMM">
        <sqoop xmlns="uri:oozie:sqoop-action:0.2">
			<job-tracker>${jobTracker}</job-tracker>
            <name-node>${nameNode}</name-node>
			<prepare>
            	<delete path="${job_SPMM_C1_OWNER_PartType_DoFullTarget}" />
            </prepare>         	
            <arg>import</arg>
         	<arg>--connect</arg>
            <arg>jdbc:sqlserver://172.23.236.90:1433;database=SPMM_C1_OWNER</arg>
            <arg>--username</arg>
            <arg>usrSqoop</arg>
            <arg>--password</arg>
            <arg>AXm6Sn6#o</arg>
            <arg>--query</arg>
            <arg>SELECT PartTypeID,PartType,Description,PartTypeCode,Variant1TagListID,Variant2TagListID,Variant3TagListID,Variant4TagListID,Variant5TagListID,Variant6TagListID,Variant7TagListID,Variant8TagListID,Variant9TagListID,Variant10TagListID,Variant11TagListID,Variant12TagListID,Variant13TagListID,Variant14TagListID,Variant15TagListID,Variant16TagListID,Variant17TagListID,Variant18TagListID,Variant19TagListID,Variant20TagListID,RfInventoryAccountingModeID, 2 as "org_id",  'SPMM' as "org_name"   FROM dbo.PartType WHERE ( $CONDITIONS ) </arg>
            <arg>--num-mappers</arg>
            <arg>1</arg>
            <arg>--target-dir</arg>
            <arg>${job_SPMM_C1_OWNER_PartType_DoFullTarget}</arg>
            <arg>--fields-terminated-by</arg>
            <arg>\t</arg>
            <arg>--direct</arg>
            <arg>--</arg>
            <arg>--schema</arg>
            <arg>dbo</arg>
            <arg>-validate</arg>
        </sqoop>
        <ok to="ProductType-Ingest-SPMM-Decision"/>
        <error to="ProductType-Ingest-SPMM-Decision"/>
    </action>

	<decision name="ProductType-Ingest-SPMM-Decision">
    	<switch>
			<case to="ProductType-Ingest-SPMM">${ wf:conf('job_SPMM_C1_OWNER_ProductType_DoFull') eq 'true'}</case>
            <default to="ScrapReasonGroup-Ingest-SPMM-Decision"/>
        </switch>
    </decision>

    <action name="ProductType-Ingest-SPMM">
        <sqoop xmlns="uri:oozie:sqoop-action:0.2">
			<job-tracker>${jobTracker}</job-tracker>
            <name-node>${nameNode}</name-node>
			<prepare>
            	<delete path="${job_SPMM_C1_OWNER_ProductType_DoFullTarget}" />
            </prepare>         	
            <arg>import</arg>
         	<arg>--connect</arg>
            <arg>jdbc:sqlserver://172.23.236.90:1433;database=SPMM_C1_OWNER</arg>
            <arg>--username</arg>
            <arg>usrSqoop</arg>
            <arg>--password</arg>
            <arg>AXm6Sn6#o</arg>
            <arg>--query</arg>
            <arg>SELECT ProductTypeID,Name,ProductTypeCode,Variant1TagListID,Variant2TagListID,Variant3TagListID,Variant4TagListID,Variant5TagListID,Variant6TagListID,Variant7TagListID,Variant8TagListID,Variant9TagListID,Variant10TagListID,Variant11TagListID,Variant12TagListID,Variant13TagListID,Variant14TagListID,Variant15TagListID,Variant16TagListID,Variant17TagListID,Variant18TagListID,Variant19TagListID,Variant20TagListID, 2 as "org_id",  'SPMM' as "org_name"   FROM dbo.ProductType WHERE ( $CONDITIONS ) </arg>
            <arg>--num-mappers</arg>
            <arg>1</arg>
            <arg>--target-dir</arg>
            <arg>${job_SPMM_C1_OWNER_ProductType_DoFullTarget}</arg>
            <arg>--fields-terminated-by</arg>
            <arg>\t</arg>
            <arg>--direct</arg>
            <arg>--</arg>
            <arg>--schema</arg>
            <arg>dbo</arg>
            <arg>-validate</arg>
        </sqoop>
        <ok to="ScrapReasonGroup-Ingest-SPMM-Decision"/>
        <error to="ScrapReasonGroup-Ingest-SPMM-Decision"/>
    </action>

	<decision name="ScrapReasonGroup-Ingest-SPMM-Decision">
    	<switch>
			<case to="ScrapReasonGroup-Ingest-SPMM">${ wf:conf('job_SPMM_C1_OWNER_ScrapReasonGroup_DoFull') eq 'true'}</case>
            <default to="ShiftPattern-Ingest-SPMM-Decision"/>
        </switch>
    </decision>

    <action name="ScrapReasonGroup-Ingest-SPMM">
        <sqoop xmlns="uri:oozie:sqoop-action:0.2">
			<job-tracker>${jobTracker}</job-tracker>
            <name-node>${nameNode}</name-node>
			<prepare>
            	<delete path="${job_SPMM_C1_OWNER_ScrapReasonGroup_DoFullTarget}" />
            </prepare>         	
            <arg>import</arg>
         	<arg>--connect</arg>
            <arg>jdbc:sqlserver://172.23.236.90:1433;database=SPMM_C1_OWNER</arg>
            <arg>--username</arg>
            <arg>usrSqoop</arg>
            <arg>--password</arg>
            <arg>AXm6Sn6#o</arg>
            <arg>--query</arg>
            <arg>SELECT ScrapReasonGroupID,ScrapReasonGroup,Description, 2 as "org_id",  'SPMM' as "org_name"   FROM dbo.ScrapReasonGroup WHERE ( $CONDITIONS ) </arg>
            <arg>--num-mappers</arg>
            <arg>1</arg>
            <arg>--target-dir</arg>
            <arg>${job_SPMM_C1_OWNER_ScrapReasonGroup_DoFullTarget}</arg>
            <arg>--fields-terminated-by</arg>
            <arg>\t</arg>
            <arg>--direct</arg>
            <arg>--</arg>
            <arg>--schema</arg>
            <arg>dbo</arg>
            <arg>-validate</arg>
        </sqoop>
        <ok to="ShiftPattern-Ingest-SPMM-Decision"/>
        <error to="ShiftPattern-Ingest-SPMM-Decision"/>
    </action>

	<decision name="ShiftPattern-Ingest-SPMM-Decision">
    	<switch>
			<case to="ShiftPattern-Ingest-SPMM">${ wf:conf('job_SPMM_C1_OWNER_ShiftPattern_DoFull') eq 'true'}</case>
            <default to="SPCChartDef-Ingest-SPMM-Decision"/>
        </switch>
    </decision>

    <action name="ShiftPattern-Ingest-SPMM">
        <sqoop xmlns="uri:oozie:sqoop-action:0.2">
			<job-tracker>${jobTracker}</job-tracker>
            <name-node>${nameNode}</name-node>
			<prepare>
            	<delete path="${job_SPMM_C1_OWNER_ShiftPattern_DoFullTarget}" />
            </prepare>         	
            <arg>import</arg>
         	<arg>--connect</arg>
            <arg>jdbc:sqlserver://172.23.236.90:1433;database=SPMM_C1_OWNER</arg>
            <arg>--username</arg>
            <arg>usrSqoop</arg>
            <arg>--password</arg>
            <arg>AXm6Sn6#o</arg>
            <arg>--query</arg>
            <arg>SELECT ShiftPatternID,ShiftPattern,PatternDuration,IsPatternDirty,IsCustomPeriod, 2 as "org_id",  'SPMM' as "org_name"   FROM dbo.ShiftPattern WHERE ( $CONDITIONS ) </arg>
            <arg>--num-mappers</arg>
            <arg>1</arg>
            <arg>--target-dir</arg>
            <arg>${job_SPMM_C1_OWNER_ShiftPattern_DoFullTarget}</arg>
            <arg>--fields-terminated-by</arg>
            <arg>\t</arg>
            <arg>--direct</arg>
            <arg>--</arg>
            <arg>--schema</arg>
            <arg>dbo</arg>
            <arg>-validate</arg>
        </sqoop>
        <ok to="SPCChartDef-Ingest-SPMM-Decision"/>
        <error to="SPCChartDef-Ingest-SPMM-Decision"/>
    </action>

	<decision name="SPCChartDef-Ingest-SPMM-Decision">
    	<switch>
			<case to="SPCChartDef-Ingest-SPMM">${ wf:conf('job_SPMM_C1_OWNER_SPCChartDef_DoFull') eq 'true'}</case>
            <default to="SPCRule-Ingest-SPMM-Decision"/>
        </switch>
    </decision>

    <action name="SPCChartDef-Ingest-SPMM">
        <sqoop xmlns="uri:oozie:sqoop-action:0.2">
			<job-tracker>${jobTracker}</job-tracker>
            <name-node>${nameNode}</name-node>
			<prepare>
            	<delete path="${job_SPMM_C1_OWNER_SPCChartDef_DoFullTarget}" />
            </prepare>         	
            <arg>import</arg>
         	<arg>--connect</arg>
            <arg>jdbc:sqlserver://172.23.236.90:1433;database=SPMM_C1_OWNER</arg>
            <arg>--username</arg>
            <arg>usrSqoop</arg>
            <arg>--password</arg>
            <arg>AXm6Sn6#o</arg>
            <arg>--query</arg>
            <arg>SELECT SPCChartDefID,VariableTypeID,SPCRuleID,RfStudyTypeID,GroupingSize,MovingRange,SPCCalcStyleID,RfGroupingID,NGroupMarkerID,CpBasedOnID,CLBasedOnID, 2 as "org_id",  'SPMM' as "org_name"   FROM dbo.SPCChartDef WHERE ( $CONDITIONS ) </arg>
            <arg>--num-mappers</arg>
            <arg>1</arg>
            <arg>--target-dir</arg>
            <arg>${job_SPMM_C1_OWNER_SPCChartDef_DoFullTarget}</arg>
            <arg>--fields-terminated-by</arg>
            <arg>\t</arg>
            <arg>--direct</arg>
            <arg>--</arg>
            <arg>--schema</arg>
            <arg>dbo</arg>
            <arg>-validate</arg>
        </sqoop>
        <ok to="SPCRule-Ingest-SPMM-Decision"/>
        <error to="SPCRule-Ingest-SPMM-Decision"/>
    </action>

	<decision name="SPCRule-Ingest-SPMM-Decision">
    	<switch>
			<case to="SPCRule-Ingest-SPMM">${ wf:conf('job_SPMM_C1_OWNER_SPCRule_DoFull') eq 'true'}</case>
            <default to="TagDefect-Ingest-SPMM-Decision"/>
        </switch>
    </decision>

    <action name="SPCRule-Ingest-SPMM">
        <sqoop xmlns="uri:oozie:sqoop-action:0.2">
			<job-tracker>${jobTracker}</job-tracker>
            <name-node>${nameNode}</name-node>
			<prepare>
            	<delete path="${job_SPMM_C1_OWNER_SPCRule_DoFullTarget}" />
            </prepare>         	
            <arg>import</arg>
         	<arg>--connect</arg>
            <arg>jdbc:sqlserver://172.23.236.90:1433;database=SPMM_C1_OWNER</arg>
            <arg>--username</arg>
            <arg>usrSqoop</arg>
            <arg>--password</arg>
            <arg>AXm6Sn6#o</arg>
            <arg>--query</arg>
            <arg>SELECT SPCRuleID,SPCRule,TAGMSTYPE1ID, 2 as "org_id",  'SPMM' as "org_name"   FROM dbo.SPCRule WHERE ( $CONDITIONS ) </arg>
            <arg>--num-mappers</arg>
            <arg>1</arg>
            <arg>--target-dir</arg>
            <arg>${job_SPMM_C1_OWNER_SPCRule_DoFullTarget}</arg>
            <arg>--fields-terminated-by</arg>
            <arg>\t</arg>
            <arg>--direct</arg>
            <arg>--</arg>
            <arg>--schema</arg>
            <arg>dbo</arg>
            <arg>-validate</arg>
        </sqoop>
        <ok to="TagDefect-Ingest-SPMM-Decision"/>
        <error to="TagDefect-Ingest-SPMM-Decision"/>
    </action>

	<decision name="TagDefect-Ingest-SPMM-Decision">
    	<switch>
			<case to="TagDefect-Ingest-SPMM">${ wf:conf('job_SPMM_C1_OWNER_TagDefect_DoFull') eq 'true'}</case>
            <default to="TagTree-Ingest-SPMM-Decision"/>
        </switch>
    </decision>

    <action name="TagDefect-Ingest-SPMM">
        <sqoop xmlns="uri:oozie:sqoop-action:0.2">
			<job-tracker>${jobTracker}</job-tracker>
            <name-node>${nameNode}</name-node>
			<prepare>
            	<delete path="${job_SPMM_C1_OWNER_TagDefect_DoFullTarget}" />
            </prepare>         	
            <arg>import</arg>
         	<arg>--connect</arg>
            <arg>jdbc:sqlserver://172.23.236.90:1433;database=SPMM_C1_OWNER</arg>
            <arg>--username</arg>
            <arg>usrSqoop</arg>
            <arg>--password</arg>
            <arg>AXm6Sn6#o</arg>
            <arg>--query</arg>
            <arg>SELECT TagDefectID,IndividualDefectID,TagTypeID,TagValue,DT,X,Y, 2 as "org_id",  'SPMM' as "org_name"   FROM dbo.TagDefect WHERE ( $CONDITIONS ) </arg>
            <arg>--num-mappers</arg>
            <arg>1</arg>
            <arg>--target-dir</arg>
            <arg>${job_SPMM_C1_OWNER_TagDefect_DoFullTarget}</arg>
            <arg>--fields-terminated-by</arg>
            <arg>\t</arg>
            <arg>--direct</arg>
            <arg>--</arg>
            <arg>--schema</arg>
            <arg>dbo</arg>
            <arg>-validate</arg>
        </sqoop>
        <ok to="TagTree-Ingest-SPMM-Decision"/>
        <error to="TagTree-Ingest-SPMM-Decision"/>
    </action>

	<decision name="TagTree-Ingest-SPMM-Decision">
    	<switch>
			<case to="TagTree-Ingest-SPMM">${ wf:conf('job_SPMM_C1_OWNER_TagTree_DoFull') eq 'true'}</case>
            <default to="TMP_Job_Shift_Downtime-Ingest-SPMM-Decision"/>
        </switch>
    </decision>

    <action name="TagTree-Ingest-SPMM">
        <sqoop xmlns="uri:oozie:sqoop-action:0.2">
			<job-tracker>${jobTracker}</job-tracker>
            <name-node>${nameNode}</name-node>
			<prepare>
            	<delete path="${job_SPMM_C1_OWNER_TagTree_DoFullTarget}" />
            </prepare>         	
            <arg>import</arg>
         	<arg>--connect</arg>
            <arg>jdbc:sqlserver://172.23.236.90:1433;database=SPMM_C1_OWNER</arg>
            <arg>--username</arg>
            <arg>usrSqoop</arg>
            <arg>--password</arg>
            <arg>AXm6Sn6#o</arg>
            <arg>--query</arg>
            <arg>SELECT TagTreeID,TagTree, 2 as "org_id",  'SPMM' as "org_name"   FROM dbo.TagTree WHERE ( $CONDITIONS ) </arg>
            <arg>--num-mappers</arg>
            <arg>1</arg>
            <arg>--target-dir</arg>
            <arg>${job_SPMM_C1_OWNER_TagTree_DoFullTarget}</arg>
            <arg>--fields-terminated-by</arg>
            <arg>\t</arg>
            <arg>--direct</arg>
            <arg>--</arg>
            <arg>--schema</arg>
            <arg>dbo</arg>
            <arg>-validate</arg>
        </sqoop>
        <ok to="TMP_Job_Shift_Downtime-Ingest-SPMM-Decision"/>
        <error to="TMP_Job_Shift_Downtime-Ingest-SPMM-Decision"/>
    </action>

	<decision name="TMP_Job_Shift_Downtime-Ingest-SPMM-Decision">
    	<switch>
			<case to="TMP_Job_Shift_Downtime-Ingest-SPMM">${ wf:conf('job_SPMM_C1_OWNER_TMP_Job_Shift_Downtime_DoFull') eq 'true'}</case>
            <default to="ToolCavity-Ingest-SPMM-Decision"/>
        </switch>
    </decision>

    <action name="TMP_Job_Shift_Downtime-Ingest-SPMM">
        <sqoop xmlns="uri:oozie:sqoop-action:0.2">
			<job-tracker>${jobTracker}</job-tracker>
            <name-node>${nameNode}</name-node>
			<prepare>
            	<delete path="${job_SPMM_C1_OWNER_TMP_Job_Shift_Downtime_DoFullTarget}" />
            </prepare>         	
            <arg>import</arg>
         	<arg>--connect</arg>
            <arg>jdbc:sqlserver://172.23.236.90:1433;database=SPMM_C1_OWNER</arg>
            <arg>--username</arg>
            <arg>usrSqoop</arg>
            <arg>--password</arg>
            <arg>AXm6Sn6#o</arg>
            <arg>--query</arg>
            <arg>SELECT ShiftID,MachineStageID,JobID,Downtime, 2 as "org_id",  'SPMM' as "org_name"   FROM dbo.TMP_Job_Shift_Downtime WHERE ( $CONDITIONS ) </arg>
            <arg>--num-mappers</arg>
            <arg>1</arg>
            <arg>--target-dir</arg>
            <arg>${job_SPMM_C1_OWNER_TMP_Job_Shift_Downtime_DoFullTarget}</arg>
            <arg>--fields-terminated-by</arg>
            <arg>\t</arg>
            <arg>--direct</arg>
            <arg>--</arg>
            <arg>--schema</arg>
            <arg>dbo</arg>
            <arg>-validate</arg>
        </sqoop>
        <ok to="ToolCavity-Ingest-SPMM-Decision"/>
        <error to="ToolCavity-Ingest-SPMM-Decision"/>
    </action>

	<decision name="ToolCavity-Ingest-SPMM-Decision">
    	<switch>
			<case to="ToolCavity-Ingest-SPMM">${ wf:conf('job_SPMM_C1_OWNER_ToolCavity_DoFull') eq 'true'}</case>
            <default to="ToolUsage-Ingest-SPMM-Decision"/>
        </switch>
    </decision>

    <action name="ToolCavity-Ingest-SPMM">
        <sqoop xmlns="uri:oozie:sqoop-action:0.2">
			<job-tracker>${jobTracker}</job-tracker>
            <name-node>${nameNode}</name-node>
			<prepare>
            	<delete path="${job_SPMM_C1_OWNER_ToolCavity_DoFullTarget}" />
            </prepare>         	
            <arg>import</arg>
         	<arg>--connect</arg>
            <arg>jdbc:sqlserver://172.23.236.90:1433;database=SPMM_C1_OWNER</arg>
            <arg>--username</arg>
            <arg>usrSqoop</arg>
            <arg>--password</arg>
            <arg>AXm6Sn6#o</arg>
            <arg>--query</arg>
            <arg>SELECT ToolCavityID,CavityNumber,CavityName,ToolID, 2 as "org_id",  'SPMM' as "org_name"   FROM dbo.ToolCavity WHERE ( $CONDITIONS ) </arg>
            <arg>--num-mappers</arg>
            <arg>1</arg>
            <arg>--target-dir</arg>
            <arg>${job_SPMM_C1_OWNER_ToolCavity_DoFullTarget}</arg>
            <arg>--fields-terminated-by</arg>
            <arg>\t</arg>
            <arg>--direct</arg>
            <arg>--</arg>
            <arg>--schema</arg>
            <arg>dbo</arg>
            <arg>-validate</arg>
        </sqoop>
        <ok to="ToolUsage-Ingest-SPMM-Decision"/>
        <error to="ToolUsage-Ingest-SPMM-Decision"/>
    </action>

	<decision name="ToolUsage-Ingest-SPMM-Decision">
    	<switch>
			<case to="ToolUsage-Ingest-SPMM">${ wf:conf('job_SPMM_C1_OWNER_ToolUsage_DoFull') eq 'true'}</case>
            <default to="UnitCountType-Ingest-SPMM-Decision"/>
        </switch>
    </decision>

    <action name="ToolUsage-Ingest-SPMM">
        <sqoop xmlns="uri:oozie:sqoop-action:0.2">
			<job-tracker>${jobTracker}</job-tracker>
            <name-node>${nameNode}</name-node>
			<prepare>
            	<delete path="${job_SPMM_C1_OWNER_ToolUsage_DoFullTarget}" />
            </prepare>         	
            <arg>import</arg>
         	<arg>--connect</arg>
            <arg>jdbc:sqlserver://172.23.236.90:1433;database=SPMM_C1_OWNER</arg>
            <arg>--username</arg>
            <arg>usrSqoop</arg>
            <arg>--password</arg>
            <arg>AXm6Sn6#o</arg>
            <arg>--query</arg>
            <arg>SELECT ToolUsageID,JobID,MachineStageID,ToolID,FromDT,ToDT,ToolPosition,ToolChangeReasonID,IsEdited,RevisionNo,OperationID, 2 as "org_id",  'SPMM' as "org_name"   FROM dbo.ToolUsage WHERE ( $CONDITIONS ) </arg>
            <arg>--num-mappers</arg>
            <arg>1</arg>
            <arg>--target-dir</arg>
            <arg>${job_SPMM_C1_OWNER_ToolUsage_DoFullTarget}</arg>
            <arg>--fields-terminated-by</arg>
            <arg>\t</arg>
            <arg>--direct</arg>
            <arg>--</arg>
            <arg>--schema</arg>
            <arg>dbo</arg>
            <arg>-validate</arg>
        </sqoop>
        <ok to="UnitCountType-Ingest-SPMM-Decision"/>
        <error to="UnitCountType-Ingest-SPMM-Decision"/>
    </action>

	<decision name="UnitCountType-Ingest-SPMM-Decision">
    	<switch>
			<case to="UnitCountType-Ingest-SPMM">${ wf:conf('job_SPMM_C1_OWNER_UnitCountType_DoFull') eq 'true'}</case>
            <default to="VariableTypeGroup-Ingest-SPMM-Decision"/>
        </switch>
    </decision>

    <action name="UnitCountType-Ingest-SPMM">
        <sqoop xmlns="uri:oozie:sqoop-action:0.2">
			<job-tracker>${jobTracker}</job-tracker>
            <name-node>${nameNode}</name-node>
			<prepare>
            	<delete path="${job_SPMM_C1_OWNER_UnitCountType_DoFullTarget}" />
            </prepare>         	
            <arg>import</arg>
         	<arg>--connect</arg>
            <arg>jdbc:sqlserver://172.23.236.90:1433;database=SPMM_C1_OWNER</arg>
            <arg>--username</arg>
            <arg>usrSqoop</arg>
            <arg>--password</arg>
            <arg>AXm6Sn6#o</arg>
            <arg>--query</arg>
            <arg>SELECT UnitCountTypeID,UnitCountType,Description,MachineStageTypeID,DefaultUnitID,IsQuantityIn,IsQuantityOut,IsMaintenanceCount,IsConvertableToBaseUnits,AssetCountTypeID, 2 as "org_id",  'SPMM' as "org_name"   FROM dbo.UnitCountType WHERE ( $CONDITIONS ) </arg>
            <arg>--num-mappers</arg>
            <arg>1</arg>
            <arg>--target-dir</arg>
            <arg>${job_SPMM_C1_OWNER_UnitCountType_DoFullTarget}</arg>
            <arg>--fields-terminated-by</arg>
            <arg>\t</arg>
            <arg>--direct</arg>
            <arg>--</arg>
            <arg>--schema</arg>
            <arg>dbo</arg>
            <arg>-validate</arg>
        </sqoop>
        <ok to="VariableTypeGroup-Ingest-SPMM-Decision"/>
        <error to="VariableTypeGroup-Ingest-SPMM-Decision"/>
    </action>

	<decision name="VariableTypeGroup-Ingest-SPMM-Decision">
    	<switch>
			<case to="VariableTypeGroup-Ingest-SPMM">${ wf:conf('job_SPMM_C1_OWNER_VariableTypeGroup_DoFull') eq 'true'}</case>
            <default to="WORef-Ingest-SPMM-Decision"/>
        </switch>
    </decision>

    <action name="VariableTypeGroup-Ingest-SPMM">
        <sqoop xmlns="uri:oozie:sqoop-action:0.2">
			<job-tracker>${jobTracker}</job-tracker>
            <name-node>${nameNode}</name-node>
			<prepare>
            	<delete path="${job_SPMM_C1_OWNER_VariableTypeGroup_DoFullTarget}" />
            </prepare>         	
            <arg>import</arg>
         	<arg>--connect</arg>
            <arg>jdbc:sqlserver://172.23.236.90:1433;database=SPMM_C1_OWNER</arg>
            <arg>--username</arg>
            <arg>usrSqoop</arg>
            <arg>--password</arg>
            <arg>AXm6Sn6#o</arg>
            <arg>--query</arg>
            <arg>SELECT VariableTypeGroupID,Name,Description,VariableTypeGroupCode,IsSmartGroup,SmartGroupPattern, 2 as "org_id",  'SPMM' as "org_name"   FROM dbo.VariableTypeGroup WHERE ( $CONDITIONS ) </arg>
            <arg>--num-mappers</arg>
            <arg>1</arg>
            <arg>--target-dir</arg>
            <arg>${job_SPMM_C1_OWNER_VariableTypeGroup_DoFullTarget}</arg>
            <arg>--fields-terminated-by</arg>
            <arg>\t</arg>
            <arg>--direct</arg>
            <arg>--</arg>
            <arg>--schema</arg>
            <arg>dbo</arg>
            <arg>-validate</arg>
        </sqoop>
        <ok to="WORef-Ingest-SPMM-Decision"/>
        <error to="WORef-Ingest-SPMM-Decision"/>
    </action>

	<decision name="WORef-Ingest-SPMM-Decision">
    	<switch>
			<case to="WORef-Ingest-SPMM">${ wf:conf('job_SPMM_C1_OWNER_WORef_DoFull') eq 'true'}</case>
            <default to="Line-Ingest-SPTT-Decision"/>
        </switch>
    </decision>

    <action name="WORef-Ingest-SPMM">
        <sqoop xmlns="uri:oozie:sqoop-action:0.2">
			<job-tracker>${jobTracker}</job-tracker>
            <name-node>${nameNode}</name-node>
			<prepare>
            	<delete path="${job_SPMM_C1_OWNER_WORef_DoFullTarget}" />
            </prepare>         	
            <arg>import</arg>
         	<arg>--connect</arg>
            <arg>jdbc:sqlserver://172.23.236.90:1433;database=SPMM_C1_OWNER</arg>
            <arg>--username</arg>
            <arg>usrSqoop</arg>
            <arg>--password</arg>
            <arg>AXm6Sn6#o</arg>
            <arg>--query</arg>
            <arg>SELECT WORefID,WOReference, 2 as "org_id",  'SPMM' as "org_name"   FROM dbo.WORef WHERE ( $CONDITIONS ) </arg>
            <arg>--num-mappers</arg>
            <arg>1</arg>
            <arg>--target-dir</arg>
            <arg>${job_SPMM_C1_OWNER_WORef_DoFullTarget}</arg>
            <arg>--fields-terminated-by</arg>
            <arg>\t</arg>
            <arg>--direct</arg>
            <arg>--</arg>
            <arg>--schema</arg>
            <arg>dbo</arg>
            <arg>-validate</arg>
        </sqoop>
        <ok to="Line-Ingest-SPTT-Decision"/>
        <error to="Line-Ingest-SPTT-Decision"/>
    </action>

	<decision name="Line-Ingest-SPTT-Decision">
    	<switch>
			<case to="Line-Ingest-SPTT">${ wf:conf('job_TOULOUSE_OWNER_Line_DoFull') eq 'true'}</case>
            <default to="End-Full-28-Ingest-Decision"/>
        </switch>
    </decision>

    <action name="Line-Ingest-SPTT">
        <sqoop xmlns="uri:oozie:sqoop-action:0.2">
			<job-tracker>${jobTracker}</job-tracker>
            <name-node>${nameNode}</name-node>
			<prepare>
            	<delete path="${job_TOULOUSE_OWNER_Line_DoFullTarget}" />
            </prepare>         	
            <arg>import</arg>
         	<arg>--connect</arg>
            <arg>jdbc:sqlserver://172.23.236.90:1433;database=TOULOUSE_OWNER</arg>
            <arg>--username</arg>
            <arg>usrSqoop</arg>
            <arg>--password</arg>
            <arg>AXm6Sn6#o</arg>
            <arg>--query</arg>
            <arg>SELECT Line.LineID, Line.Line, Line.Description, Line.LineTypeID, Line.IsRetired, Line.RfIntervalModeID, Line.IsOEEInventoryIsolation, Line.IsOEEInventoryReintroduction, Line.IsCountOutputInventory, Line.IsCountInputInventory, Line.IsLineInfoSweepEnabled, Line.IsWOOnSingleJob, Line.LineShortName, Line.CurrentLineInfoID, Line.LastLineInfoID, Line.RfInvCreatedDateModeID, Line.RfEndJobInvModeID, Line.CurrentJobID, Line.IsScrapAsQualityLoss, Line.IsScrapInProductionCounts, Line.LineDownCostPerHour, Line.IsContributeLineGroupOutput, Line.IsContributeLineGroupWaste, Line.IsContributeLineGroupDowntime, Line_.OEETarget, Line_.WasteTarget, Line_.Reference1, Line_.Reference2, Line_.Reference3, Line_.Reference4, Line_.Reference5,  4 as "org_id",  'SPTT' as "org_name"  FROM Line FULL JOIN Line_ ON (Line.LineID = Line_.LineID) FULL JOIN Line_Custom ON (Line.LineID = Line_Custom.LineID)   WHERE ( $CONDITIONS ) </arg>
            <arg>--num-mappers</arg>
            <arg>1</arg>
            <arg>--target-dir</arg>
            <arg>${job_TOULOUSE_OWNER_Line_DoFullTarget}</arg>
            <arg>--fields-terminated-by</arg>
            <arg>\t</arg>
            <arg>--direct</arg>
            <arg>--</arg>
            <arg>--schema</arg>
            <arg>dbo</arg>
            <arg>-validate</arg>
        </sqoop>
        <ok to="End-Full-28-Ingest-Decision"/>
        <error to="End-Full-28-Ingest-Decision"/>
    </action>

	<end name="End-Full-28-Ingest-Decision"/>
</workflow-app>
