<workflow-app name="Ingest-Full-25" xmlns="uri:oozie:workflow:0.1">

 	<start to="AcquisitionAttributeType-Ingest-SPDV-Decision"/>


	<decision name="AcquisitionAttributeType-Ingest-SPDV-Decision">
    	<switch>
			<case to="AcquisitionAttributeType-Ingest-SPDV">${ wf:conf('job_DEVERN_OWNER_AcquisitionAttributeType_DoFull') eq 'true'}</case>
            <default to="AcquisitionVariant-Ingest-SPDV-Decision"/>
        </switch>
    </decision>

    <action name="AcquisitionAttributeType-Ingest-SPDV">
        <sqoop xmlns="uri:oozie:sqoop-action:0.2">
			<job-tracker>${jobTracker}</job-tracker>
            <name-node>${nameNode}</name-node>
			<prepare>
            	<delete path="${job_DEVERN_OWNER_AcquisitionAttributeType_DoFullTarget}" />
            </prepare>         	
            <arg>import</arg>
         	<arg>--connect</arg>
            <arg>jdbc:sqlserver://172.23.236.90:1433;database=DEVERN_OWNER</arg>
            <arg>--username</arg>
            <arg>usrSqoop</arg>
            <arg>--password</arg>
            <arg>AXm6Sn6#o</arg>
            <arg>--query</arg>
            <arg>SELECT AcquisitionAttributeTypeID,AcquisitionVariantID,AttributeTypeID,EntryOrder,Formula,IsExplicitStep, 3 as "org_id",  'SPDV' as "org_name"   FROM dbo.AcquisitionAttributeType WHERE ( $CONDITIONS ) </arg>
            <arg>--num-mappers</arg>
            <arg>1</arg>
            <arg>--target-dir</arg>
            <arg>${job_DEVERN_OWNER_AcquisitionAttributeType_DoFullTarget}</arg>
            <arg>--fields-terminated-by</arg>
            <arg>\t</arg>
            <arg>--direct</arg>
            <arg>--</arg>
            <arg>--schema</arg>
            <arg>dbo</arg>
            <arg>-validate</arg>
        </sqoop>
        <ok to="AcquisitionVariant-Ingest-SPDV-Decision"/>
        <error to="AcquisitionVariant-Ingest-SPDV-Decision"/>
    </action>

	<decision name="AcquisitionVariant-Ingest-SPDV-Decision">
    	<switch>
			<case to="AcquisitionVariant-Ingest-SPDV">${ wf:conf('job_DEVERN_OWNER_AcquisitionVariant_DoFull') eq 'true'}</case>
            <default to="ActionSubType-Ingest-SPDV-Decision"/>
        </switch>
    </decision>

    <action name="AcquisitionVariant-Ingest-SPDV">
        <sqoop xmlns="uri:oozie:sqoop-action:0.2">
			<job-tracker>${jobTracker}</job-tracker>
            <name-node>${nameNode}</name-node>
			<prepare>
            	<delete path="${job_DEVERN_OWNER_AcquisitionVariant_DoFullTarget}" />
            </prepare>         	
            <arg>import</arg>
         	<arg>--connect</arg>
            <arg>jdbc:sqlserver://172.23.236.90:1433;database=DEVERN_OWNER</arg>
            <arg>--username</arg>
            <arg>usrSqoop</arg>
            <arg>--password</arg>
            <arg>AXm6Sn6#o</arg>
            <arg>--query</arg>
            <arg>SELECT AcquisitionVariantID,AcquisitionID,MeasurementSetTagProfileID,PartInstanceTagProfileID,DefectTagProfileID,RfAcquisitionClassID,RfDataCollectionFreqID,DataCollectionPeriod,IsRetired,AcqPlan,VMTPID,CauseActionTPID,Variant,PartTypeID,RevisionNo,IsEdited,HeadAlias,CauseTagListID,ActionTagListID,IsMeasuredWhenProduced,IsInvPackCheck,IsEBATrigger, 3 as "org_id",  'SPDV' as "org_name"   FROM dbo.AcquisitionVariant WHERE ( $CONDITIONS ) </arg>
            <arg>--num-mappers</arg>
            <arg>1</arg>
            <arg>--target-dir</arg>
            <arg>${job_DEVERN_OWNER_AcquisitionVariant_DoFullTarget}</arg>
            <arg>--fields-terminated-by</arg>
            <arg>\t</arg>
            <arg>--direct</arg>
            <arg>--</arg>
            <arg>--schema</arg>
            <arg>dbo</arg>
            <arg>-validate</arg>
        </sqoop>
        <ok to="ActionSubType-Ingest-SPDV-Decision"/>
        <error to="ActionSubType-Ingest-SPDV-Decision"/>
    </action>

	<decision name="ActionSubType-Ingest-SPDV-Decision">
    	<switch>
			<case to="ActionSubType-Ingest-SPDV">${ wf:conf('job_DEVERN_OWNER_ActionSubType_DoFull') eq 'true'}</case>
            <default to="AssetExplosion-Ingest-SPDV-Decision"/>
        </switch>
    </decision>

    <action name="ActionSubType-Ingest-SPDV">
        <sqoop xmlns="uri:oozie:sqoop-action:0.2">
			<job-tracker>${jobTracker}</job-tracker>
            <name-node>${nameNode}</name-node>
			<prepare>
            	<delete path="${job_DEVERN_OWNER_ActionSubType_DoFullTarget}" />
            </prepare>         	
            <arg>import</arg>
         	<arg>--connect</arg>
            <arg>jdbc:sqlserver://172.23.236.90:1433;database=DEVERN_OWNER</arg>
            <arg>--username</arg>
            <arg>usrSqoop</arg>
            <arg>--password</arg>
            <arg>AXm6Sn6#o</arg>
            <arg>--query</arg>
            <arg>SELECT ActionSubTypeID,ActionSubType,ActionTypeID,Description,SubActionTypeCode,ReportOrder,Format,IsRetired, 3 as "org_id",  'SPDV' as "org_name"   FROM dbo.ActionSubType WHERE ( $CONDITIONS ) </arg>
            <arg>--num-mappers</arg>
            <arg>1</arg>
            <arg>--target-dir</arg>
            <arg>${job_DEVERN_OWNER_ActionSubType_DoFullTarget}</arg>
            <arg>--fields-terminated-by</arg>
            <arg>\t</arg>
            <arg>--direct</arg>
            <arg>--</arg>
            <arg>--schema</arg>
            <arg>dbo</arg>
            <arg>-validate</arg>
        </sqoop>
        <ok to="AssetExplosion-Ingest-SPDV-Decision"/>
        <error to="AssetExplosion-Ingest-SPDV-Decision"/>
    </action>

	<decision name="AssetExplosion-Ingest-SPDV-Decision">
    	<switch>
			<case to="AssetExplosion-Ingest-SPDV">${ wf:conf('job_DEVERN_OWNER_AssetExplosion_DoFull') eq 'true'}</case>
            <default to="AVDataEntryOptions-Ingest-SPDV-Decision"/>
        </switch>
    </decision>

    <action name="AssetExplosion-Ingest-SPDV">
        <sqoop xmlns="uri:oozie:sqoop-action:0.2">
			<job-tracker>${jobTracker}</job-tracker>
            <name-node>${nameNode}</name-node>
			<prepare>
            	<delete path="${job_DEVERN_OWNER_AssetExplosion_DoFullTarget}" />
            </prepare>         	
            <arg>import</arg>
         	<arg>--connect</arg>
            <arg>jdbc:sqlserver://172.23.236.90:1433;database=DEVERN_OWNER</arg>
            <arg>--username</arg>
            <arg>usrSqoop</arg>
            <arg>--password</arg>
            <arg>AXm6Sn6#o</arg>
            <arg>--query</arg>
            <arg>SELECT AssetID,ParentAssetID,SubAssetID,Lvl,SortOrder,Comments,AssetLevelID, 3 as "org_id",  'SPDV' as "org_name"   FROM dbo.AssetExplosion WHERE ( $CONDITIONS ) </arg>
            <arg>--num-mappers</arg>
            <arg>1</arg>
            <arg>--target-dir</arg>
            <arg>${job_DEVERN_OWNER_AssetExplosion_DoFullTarget}</arg>
            <arg>--fields-terminated-by</arg>
            <arg>\t</arg>
            <arg>--direct</arg>
            <arg>--</arg>
            <arg>--schema</arg>
            <arg>dbo</arg>
            <arg>-validate</arg>
        </sqoop>
        <ok to="AVDataEntryOptions-Ingest-SPDV-Decision"/>
        <error to="AVDataEntryOptions-Ingest-SPDV-Decision"/>
    </action>

	<decision name="AVDataEntryOptions-Ingest-SPDV-Decision">
    	<switch>
			<case to="AVDataEntryOptions-Ingest-SPDV">${ wf:conf('job_DEVERN_OWNER_AVDataEntryOptions_DoFull') eq 'true'}</case>
            <default to="Comments-Ingest-SPDV-Decision"/>
        </switch>
    </decision>

    <action name="AVDataEntryOptions-Ingest-SPDV">
        <sqoop xmlns="uri:oozie:sqoop-action:0.2">
			<job-tracker>${jobTracker}</job-tracker>
            <name-node>${nameNode}</name-node>
			<prepare>
            	<delete path="${job_DEVERN_OWNER_AVDataEntryOptions_DoFullTarget}" />
            </prepare>         	
            <arg>import</arg>
         	<arg>--connect</arg>
            <arg>jdbc:sqlserver://172.23.236.90:1433;database=DEVERN_OWNER</arg>
            <arg>--username</arg>
            <arg>usrSqoop</arg>
            <arg>--password</arg>
            <arg>AXm6Sn6#o</arg>
            <arg>--query</arg>
            <arg>SELECT AcquisitionVariantID,RfVarGridStyleID,IsPITCols,IsPISNoCol,RfAttrGridStyleID,IsStepGrid,IsAttrSkipStep,ShowAttrInfoTip,UseAttrImagePicker,AttrGridContextMenu,IsPISerial,AutoGenerateSerialNo,PITSampling,MSTSampling,VAInterlace,IsExplicitHS,SampleSizeMode,OnDataCommitGoTo,IsDisableOOSWarnings,StepEditPolicy,DisableKeyboardOverride,ChainToStopped,DisplayPlan,AttrPassFailDefault,VariableSaveMode,AttrCellClick, 3 as "org_id",  'SPDV' as "org_name"   FROM dbo.AVDataEntryOptions WHERE ( $CONDITIONS ) </arg>
            <arg>--num-mappers</arg>
            <arg>1</arg>
            <arg>--target-dir</arg>
            <arg>${job_DEVERN_OWNER_AVDataEntryOptions_DoFullTarget}</arg>
            <arg>--fields-terminated-by</arg>
            <arg>\t</arg>
            <arg>--direct</arg>
            <arg>--</arg>
            <arg>--schema</arg>
            <arg>dbo</arg>
            <arg>-validate</arg>
        </sqoop>
        <ok to="Comments-Ingest-SPDV-Decision"/>
        <error to="Comments-Ingest-SPDV-Decision"/>
    </action>

	<decision name="Comments-Ingest-SPDV-Decision">
    	<switch>
			<case to="Comments-Ingest-SPDV">${ wf:conf('job_DEVERN_OWNER_Comments_DoFull') eq 'true'}</case>
            <default to="CRN_AcquisitionVariableType-Ingest-SPDV-Decision"/>
        </switch>
    </decision>

    <action name="Comments-Ingest-SPDV">
        <sqoop xmlns="uri:oozie:sqoop-action:0.2">
			<job-tracker>${jobTracker}</job-tracker>
            <name-node>${nameNode}</name-node>
			<prepare>
            	<delete path="${job_DEVERN_OWNER_Comments_DoFullTarget}" />
            </prepare>         	
            <arg>import</arg>
         	<arg>--connect</arg>
            <arg>jdbc:sqlserver://172.23.236.90:1433;database=DEVERN_OWNER</arg>
            <arg>--username</arg>
            <arg>usrSqoop</arg>
            <arg>--password</arg>
            <arg>AXm6Sn6#o</arg>
            <arg>--query</arg>
            <arg>SELECT CommentsID,LoginID,DT,Subject,Comments, 3 as "org_id",  'SPDV' as "org_name"   FROM dbo.Comments WHERE ( $CONDITIONS ) </arg>
            <arg>--num-mappers</arg>
            <arg>1</arg>
            <arg>--target-dir</arg>
            <arg>${job_DEVERN_OWNER_Comments_DoFullTarget}</arg>
            <arg>--fields-terminated-by</arg>
            <arg>\t</arg>
            <arg>--direct</arg>
            <arg>--</arg>
            <arg>--schema</arg>
            <arg>dbo</arg>
            <arg>-validate</arg>
        </sqoop>
        <ok to="CRN_AcquisitionVariableType-Ingest-SPDV-Decision"/>
        <error to="CRN_AcquisitionVariableType-Ingest-SPDV-Decision"/>
    </action>

	<decision name="CRN_AcquisitionVariableType-Ingest-SPDV-Decision">
    	<switch>
			<case to="CRN_AcquisitionVariableType-Ingest-SPDV">${ wf:conf('job_DEVERN_OWNER_CRN_AcquisitionVariableType_DoFull') eq 'true'}</case>
            <default to="DocumentType-Ingest-SPMX-Decision"/>
        </switch>
    </decision>

    <action name="CRN_AcquisitionVariableType-Ingest-SPDV">
        <sqoop xmlns="uri:oozie:sqoop-action:0.2">
			<job-tracker>${jobTracker}</job-tracker>
            <name-node>${nameNode}</name-node>
			<prepare>
            	<delete path="${job_DEVERN_OWNER_CRN_AcquisitionVariableType_DoFullTarget}" />
            </prepare>         	
            <arg>import</arg>
         	<arg>--connect</arg>
            <arg>jdbc:sqlserver://172.23.236.90:1433;database=DEVERN_OWNER</arg>
            <arg>--username</arg>
            <arg>usrSqoop</arg>
            <arg>--password</arg>
            <arg>AXm6Sn6#o</arg>
            <arg>--query</arg>
            <arg>SELECT AcquisitionVariableTypeID,JobCommentLength,RfTorqueDirectionID,RfCycleEndTimeID,ThresholdTorque,RfMeasurementTypeID,RfFrequencyResponseID,UnitID,AuditAngle,CrnAdapterID, 3 as "org_id",  'SPDV' as "org_name"   FROM dbo.CRN_AcquisitionVariableType WHERE ( $CONDITIONS ) </arg>
            <arg>--num-mappers</arg>
            <arg>1</arg>
            <arg>--target-dir</arg>
            <arg>${job_DEVERN_OWNER_CRN_AcquisitionVariableType_DoFullTarget}</arg>
            <arg>--fields-terminated-by</arg>
            <arg>\t</arg>
            <arg>--direct</arg>
            <arg>--</arg>
            <arg>--schema</arg>
            <arg>dbo</arg>
            <arg>-validate</arg>
        </sqoop>
        <ok to="DocumentType-Ingest-SPMX-Decision"/>
        <error to="DocumentType-Ingest-SPMX-Decision"/>
    </action>

	<decision name="DocumentType-Ingest-SPMX-Decision">
    	<switch>
			<case to="DocumentType-Ingest-SPMX">${ wf:conf('job_MEXICALI_OWNER_DocumentType_DoFull') eq 'true'}</case>
            <default to="GaugeType-Ingest-SPMX-Decision"/>
        </switch>
    </decision>

    <action name="DocumentType-Ingest-SPMX">
        <sqoop xmlns="uri:oozie:sqoop-action:0.2">
			<job-tracker>${jobTracker}</job-tracker>
            <name-node>${nameNode}</name-node>
			<prepare>
            	<delete path="${job_MEXICALI_OWNER_DocumentType_DoFullTarget}" />
            </prepare>         	
            <arg>import</arg>
         	<arg>--connect</arg>
            <arg>jdbc:sqlserver://172.23.236.90:1433;database=MEXICALI_OWNER</arg>
            <arg>--username</arg>
            <arg>usrSqoop</arg>
            <arg>--password</arg>
            <arg>AXm6Sn6#o</arg>
            <arg>--query</arg>
            <arg>SELECT DocumentTypeID,DocumentType, 1 as "org_id",  'SPMX' as "org_name"   FROM dbo.DocumentType WHERE ( $CONDITIONS ) </arg>
            <arg>--num-mappers</arg>
            <arg>1</arg>
            <arg>--target-dir</arg>
            <arg>${job_MEXICALI_OWNER_DocumentType_DoFullTarget}</arg>
            <arg>--fields-terminated-by</arg>
            <arg>\t</arg>
            <arg>--direct</arg>
            <arg>--</arg>
            <arg>--schema</arg>
            <arg>dbo</arg>
            <arg>-validate</arg>
        </sqoop>
        <ok to="GaugeType-Ingest-SPMX-Decision"/>
        <error to="GaugeType-Ingest-SPMX-Decision"/>
    </action>

	<decision name="GaugeType-Ingest-SPMX-Decision">
    	<switch>
			<case to="GaugeType-Ingest-SPMX">${ wf:conf('job_MEXICALI_OWNER_GaugeType_DoFull') eq 'true'}</case>
            <default to="LineCell-Ingest-SPDV-Decision"/>
        </switch>
    </decision>

    <action name="GaugeType-Ingest-SPMX">
        <sqoop xmlns="uri:oozie:sqoop-action:0.2">
			<job-tracker>${jobTracker}</job-tracker>
            <name-node>${nameNode}</name-node>
			<prepare>
            	<delete path="${job_MEXICALI_OWNER_GaugeType_DoFullTarget}" />
            </prepare>         	
            <arg>import</arg>
         	<arg>--connect</arg>
            <arg>jdbc:sqlserver://172.23.236.90:1433;database=MEXICALI_OWNER</arg>
            <arg>--username</arg>
            <arg>usrSqoop</arg>
            <arg>--password</arg>
            <arg>AXm6Sn6#o</arg>
            <arg>--query</arg>
            <arg>SELECT GaugeTypeID,GaugeType, 1 as "org_id",  'SPMX' as "org_name"   FROM dbo.GaugeType WHERE ( $CONDITIONS ) </arg>
            <arg>--num-mappers</arg>
            <arg>1</arg>
            <arg>--target-dir</arg>
            <arg>${job_MEXICALI_OWNER_GaugeType_DoFullTarget}</arg>
            <arg>--fields-terminated-by</arg>
            <arg>\t</arg>
            <arg>--direct</arg>
            <arg>--</arg>
            <arg>--schema</arg>
            <arg>dbo</arg>
            <arg>-validate</arg>
        </sqoop>
        <ok to="LineCell-Ingest-SPDV-Decision"/>
        <error to="LineCell-Ingest-SPDV-Decision"/>
    </action>

	<decision name="LineCell-Ingest-SPDV-Decision">
    	<switch>
			<case to="LineCell-Ingest-SPDV">${ wf:conf('job_DEVERN_OWNER_LineCell_DoFull') eq 'true'}</case>
            <default to="LkAGAV-Ingest-SPMX-Decision"/>
        </switch>
    </decision>

    <action name="LineCell-Ingest-SPDV">
        <sqoop xmlns="uri:oozie:sqoop-action:0.2">
			<job-tracker>${jobTracker}</job-tracker>
            <name-node>${nameNode}</name-node>
			<prepare>
            	<delete path="${job_DEVERN_OWNER_LineCell_DoFullTarget}" />
            </prepare>         	
            <arg>import</arg>
         	<arg>--connect</arg>
            <arg>jdbc:sqlserver://172.23.236.90:1433;database=DEVERN_OWNER</arg>
            <arg>--username</arg>
            <arg>usrSqoop</arg>
            <arg>--password</arg>
            <arg>AXm6Sn6#o</arg>
            <arg>--query</arg>
            <arg>SELECT LineCellID,LineID,IsPartNumber,IsWONumber,IsCustomer,IsDescription,IsHeader,IsRows,ConfigLayout,IsClickable,IsStopJob,IsStartJob,IsEditable,IsStartNextJob,IsWORef1,IsWORef2,IsWORef3,IsWorkInstruction, 3 as "org_id",  'SPDV' as "org_name"   FROM dbo.LineCell WHERE ( $CONDITIONS ) </arg>
            <arg>--num-mappers</arg>
            <arg>1</arg>
            <arg>--target-dir</arg>
            <arg>${job_DEVERN_OWNER_LineCell_DoFullTarget}</arg>
            <arg>--fields-terminated-by</arg>
            <arg>\t</arg>
            <arg>--direct</arg>
            <arg>--</arg>
            <arg>--schema</arg>
            <arg>dbo</arg>
            <arg>-validate</arg>
        </sqoop>
        <ok to="LkAGAV-Ingest-SPMX-Decision"/>
        <error to="LkAGAV-Ingest-SPMX-Decision"/>
    </action>

	<decision name="LkAGAV-Ingest-SPMX-Decision">
    	<switch>
			<case to="LkAGAV-Ingest-SPMX">${ wf:conf('job_MEXICALI_OWNER_LkAGAV_DoFull') eq 'true'}</case>
            <default to="LkConcernRootCause-Ingest-SPMX-Decision"/>
        </switch>
    </decision>

    <action name="LkAGAV-Ingest-SPMX">
        <sqoop xmlns="uri:oozie:sqoop-action:0.2">
			<job-tracker>${jobTracker}</job-tracker>
            <name-node>${nameNode}</name-node>
			<prepare>
            	<delete path="${job_MEXICALI_OWNER_LkAGAV_DoFullTarget}" />
            </prepare>         	
            <arg>import</arg>
         	<arg>--connect</arg>
            <arg>jdbc:sqlserver://172.23.236.90:1433;database=MEXICALI_OWNER</arg>
            <arg>--username</arg>
            <arg>usrSqoop</arg>
            <arg>--password</arg>
            <arg>AXm6Sn6#o</arg>
            <arg>--query</arg>
            <arg>SELECT AcquisitionGroupID,AcquisitionVariantID,Sequence,LkAGAVID, 1 as "org_id",  'SPMX' as "org_name"   FROM dbo.LkAGAV WHERE ( $CONDITIONS ) </arg>
            <arg>--num-mappers</arg>
            <arg>1</arg>
            <arg>--target-dir</arg>
            <arg>${job_MEXICALI_OWNER_LkAGAV_DoFullTarget}</arg>
            <arg>--fields-terminated-by</arg>
            <arg>\t</arg>
            <arg>--direct</arg>
            <arg>--</arg>
            <arg>--schema</arg>
            <arg>dbo</arg>
            <arg>-validate</arg>
        </sqoop>
        <ok to="LkConcernRootCause-Ingest-SPMX-Decision"/>
        <error to="LkConcernRootCause-Ingest-SPMX-Decision"/>
    </action>

	<decision name="LkConcernRootCause-Ingest-SPMX-Decision">
    	<switch>
			<case to="LkConcernRootCause-Ingest-SPMX">${ wf:conf('job_MEXICALI_OWNER_LkConcernRootCause_DoFull') eq 'true'}</case>
            <default to="LkDocumentWIProc-Ingest-SPMX-Decision"/>
        </switch>
    </decision>

    <action name="LkConcernRootCause-Ingest-SPMX">
        <sqoop xmlns="uri:oozie:sqoop-action:0.2">
			<job-tracker>${jobTracker}</job-tracker>
            <name-node>${nameNode}</name-node>
			<prepare>
            	<delete path="${job_MEXICALI_OWNER_LkConcernRootCause_DoFullTarget}" />
            </prepare>         	
            <arg>import</arg>
         	<arg>--connect</arg>
            <arg>jdbc:sqlserver://172.23.236.90:1433;database=MEXICALI_OWNER</arg>
            <arg>--username</arg>
            <arg>usrSqoop</arg>
            <arg>--password</arg>
            <arg>AXm6Sn6#o</arg>
            <arg>--query</arg>
            <arg>SELECT LkConcernRootCauseID,RootCauseID,ConcernID, 1 as "org_id",  'SPMX' as "org_name"   FROM dbo.LkConcernRootCause WHERE ( $CONDITIONS ) </arg>
            <arg>--num-mappers</arg>
            <arg>1</arg>
            <arg>--target-dir</arg>
            <arg>${job_MEXICALI_OWNER_LkConcernRootCause_DoFullTarget}</arg>
            <arg>--fields-terminated-by</arg>
            <arg>\t</arg>
            <arg>--direct</arg>
            <arg>--</arg>
            <arg>--schema</arg>
            <arg>dbo</arg>
            <arg>-validate</arg>
        </sqoop>
        <ok to="LkDocumentWIProc-Ingest-SPMX-Decision"/>
        <error to="LkDocumentWIProc-Ingest-SPMX-Decision"/>
    </action>

	<decision name="LkDocumentWIProc-Ingest-SPMX-Decision">
    	<switch>
			<case to="LkDocumentWIProc-Ingest-SPMX">${ wf:conf('job_MEXICALI_OWNER_LkDocumentWIProc_DoFull') eq 'true'}</case>
            <default to="LkLocationMachineStage-Ingest-SPDV-Decision"/>
        </switch>
    </decision>

    <action name="LkDocumentWIProc-Ingest-SPMX">
        <sqoop xmlns="uri:oozie:sqoop-action:0.2">
			<job-tracker>${jobTracker}</job-tracker>
            <name-node>${nameNode}</name-node>
			<prepare>
            	<delete path="${job_MEXICALI_OWNER_LkDocumentWIProc_DoFullTarget}" />
            </prepare>         	
            <arg>import</arg>
         	<arg>--connect</arg>
            <arg>jdbc:sqlserver://172.23.236.90:1433;database=MEXICALI_OWNER</arg>
            <arg>--username</arg>
            <arg>usrSqoop</arg>
            <arg>--password</arg>
            <arg>AXm6Sn6#o</arg>
            <arg>--query</arg>
            <arg>SELECT LkDocumentWIProcID,WorkInstructionProcedureID,DocumentID, 1 as "org_id",  'SPMX' as "org_name"   FROM dbo.LkDocumentWIProc WHERE ( $CONDITIONS ) </arg>
            <arg>--num-mappers</arg>
            <arg>1</arg>
            <arg>--target-dir</arg>
            <arg>${job_MEXICALI_OWNER_LkDocumentWIProc_DoFullTarget}</arg>
            <arg>--fields-terminated-by</arg>
            <arg>\t</arg>
            <arg>--direct</arg>
            <arg>--</arg>
            <arg>--schema</arg>
            <arg>dbo</arg>
            <arg>-validate</arg>
        </sqoop>
        <ok to="LkLocationMachineStage-Ingest-SPDV-Decision"/>
        <error to="LkLocationMachineStage-Ingest-SPDV-Decision"/>
    </action>

	<decision name="LkLocationMachineStage-Ingest-SPDV-Decision">
    	<switch>
			<case to="LkLocationMachineStage-Ingest-SPDV">${ wf:conf('job_DEVERN_OWNER_LkLocationMachineStage_DoFull') eq 'true'}</case>
            <default to="LkOpTMST-Ingest-SPDV-Decision"/>
        </switch>
    </decision>

    <action name="LkLocationMachineStage-Ingest-SPDV">
        <sqoop xmlns="uri:oozie:sqoop-action:0.2">
			<job-tracker>${jobTracker}</job-tracker>
            <name-node>${nameNode}</name-node>
			<prepare>
            	<delete path="${job_DEVERN_OWNER_LkLocationMachineStage_DoFullTarget}" />
            </prepare>         	
            <arg>import</arg>
         	<arg>--connect</arg>
            <arg>jdbc:sqlserver://172.23.236.90:1433;database=DEVERN_OWNER</arg>
            <arg>--username</arg>
            <arg>usrSqoop</arg>
            <arg>--password</arg>
            <arg>AXm6Sn6#o</arg>
            <arg>--query</arg>
            <arg>SELECT LkLocationMachineStageId,MachineStageId,LocationId,IsLocationIn,IsLocationOut, 3 as "org_id",  'SPDV' as "org_name"   FROM dbo.LkLocationMachineStage WHERE ( $CONDITIONS ) </arg>
            <arg>--num-mappers</arg>
            <arg>1</arg>
            <arg>--target-dir</arg>
            <arg>${job_DEVERN_OWNER_LkLocationMachineStage_DoFullTarget}</arg>
            <arg>--fields-terminated-by</arg>
            <arg>\t</arg>
            <arg>--direct</arg>
            <arg>--</arg>
            <arg>--schema</arg>
            <arg>dbo</arg>
            <arg>-validate</arg>
        </sqoop>
        <ok to="LkOpTMST-Ingest-SPDV-Decision"/>
        <error to="LkOpTMST-Ingest-SPDV-Decision"/>
    </action>

	<decision name="LkOpTMST-Ingest-SPDV-Decision">
    	<switch>
			<case to="LkOpTMST-Ingest-SPDV">${ wf:conf('job_DEVERN_OWNER_LkOpTMST_DoFull') eq 'true'}</case>
            <default to="LKPartUnit-Ingest-SPTM-Decision"/>
        </switch>
    </decision>

    <action name="LkOpTMST-Ingest-SPDV">
        <sqoop xmlns="uri:oozie:sqoop-action:0.2">
			<job-tracker>${jobTracker}</job-tracker>
            <name-node>${nameNode}</name-node>
			<prepare>
            	<delete path="${job_DEVERN_OWNER_LkOpTMST_DoFullTarget}" />
            </prepare>         	
            <arg>import</arg>
         	<arg>--connect</arg>
            <arg>jdbc:sqlserver://172.23.236.90:1433;database=DEVERN_OWNER</arg>
            <arg>--username</arg>
            <arg>usrSqoop</arg>
            <arg>--password</arg>
            <arg>AXm6Sn6#o</arg>
            <arg>--query</arg>
            <arg>SELECT OperationTypeID,MachineStageTypeID,LkOpTMSTID,PassName, 3 as "org_id",  'SPDV' as "org_name"   FROM dbo.LkOpTMST WHERE ( $CONDITIONS ) </arg>
            <arg>--num-mappers</arg>
            <arg>1</arg>
            <arg>--target-dir</arg>
            <arg>${job_DEVERN_OWNER_LkOpTMST_DoFullTarget}</arg>
            <arg>--fields-terminated-by</arg>
            <arg>\t</arg>
            <arg>--direct</arg>
            <arg>--</arg>
            <arg>--schema</arg>
            <arg>dbo</arg>
            <arg>-validate</arg>
        </sqoop>
        <ok to="LKPartUnit-Ingest-SPTM-Decision"/>
        <error to="LKPartUnit-Ingest-SPTM-Decision"/>
    </action>

	<decision name="LKPartUnit-Ingest-SPTM-Decision">
    	<switch>
			<case to="LKPartUnit-Ingest-SPTM">${ wf:conf('job_CAPETOWN_OWNER_LKPartUnit_DoFull') eq 'true'}</case>
            <default to="LkTSTC-Ingest-SPTT-Decision"/>
        </switch>
    </decision>

    <action name="LKPartUnit-Ingest-SPTM">
        <sqoop xmlns="uri:oozie:sqoop-action:0.2">
			<job-tracker>${jobTracker}</job-tracker>
            <name-node>${nameNode}</name-node>
			<prepare>
            	<delete path="${job_CAPETOWN_OWNER_LKPartUnit_DoFullTarget}" />
            </prepare>         	
            <arg>import</arg>
         	<arg>--connect</arg>
            <arg>jdbc:sqlserver://172.23.236.90:1433;database=CAPETOWN_OWNER</arg>
            <arg>--username</arg>
            <arg>usrSqoop</arg>
            <arg>--password</arg>
            <arg>AXm6Sn6#o</arg>
            <arg>--query</arg>
            <arg>SELECT PartID,UnitID,LkPartUnitID, 5 as "org_id",  'SPTM' as "org_name"   FROM dbo.LKPartUnit WHERE ( $CONDITIONS ) </arg>
            <arg>--num-mappers</arg>
            <arg>1</arg>
            <arg>--target-dir</arg>
            <arg>${job_CAPETOWN_OWNER_LKPartUnit_DoFullTarget}</arg>
            <arg>--fields-terminated-by</arg>
            <arg>\t</arg>
            <arg>--direct</arg>
            <arg>--</arg>
            <arg>--schema</arg>
            <arg>dbo</arg>
            <arg>-validate</arg>
        </sqoop>
        <ok to="LkTSTC-Ingest-SPTT-Decision"/>
        <error to="LkTSTC-Ingest-SPTT-Decision"/>
    </action>

	<decision name="LkTSTC-Ingest-SPTT-Decision">
    	<switch>
			<case to="LkTSTC-Ingest-SPTT">${ wf:conf('job_TOULOUSE_OWNER_LkTSTC_DoFull') eq 'true'}</case>
            <default to="LkWIRMSetReq-Ingest-SPTT-Decision"/>
        </switch>
    </decision>

    <action name="LkTSTC-Ingest-SPTT">
        <sqoop xmlns="uri:oozie:sqoop-action:0.2">
			<job-tracker>${jobTracker}</job-tracker>
            <name-node>${nameNode}</name-node>
			<prepare>
            	<delete path="${job_TOULOUSE_OWNER_LkTSTC_DoFullTarget}" />
            </prepare>         	
            <arg>import</arg>
         	<arg>--connect</arg>
            <arg>jdbc:sqlserver://172.23.236.90:1433;database=TOULOUSE_OWNER</arg>
            <arg>--username</arg>
            <arg>usrSqoop</arg>
            <arg>--password</arg>
            <arg>AXm6Sn6#o</arg>
            <arg>--query</arg>
            <arg>SELECT ToolStateID,ToolCavityID,RfToolCavityStatusID,ToolCavityStateReasonID,IsCavityChangeState,LkTSTCID, 4 as "org_id",  'SPTT' as "org_name"   FROM dbo.LkTSTC WHERE ( $CONDITIONS ) </arg>
            <arg>--num-mappers</arg>
            <arg>1</arg>
            <arg>--target-dir</arg>
            <arg>${job_TOULOUSE_OWNER_LkTSTC_DoFullTarget}</arg>
            <arg>--fields-terminated-by</arg>
            <arg>\t</arg>
            <arg>--direct</arg>
            <arg>--</arg>
            <arg>--schema</arg>
            <arg>dbo</arg>
            <arg>-validate</arg>
        </sqoop>
        <ok to="LkWIRMSetReq-Ingest-SPTT-Decision"/>
        <error to="LkWIRMSetReq-Ingest-SPTT-Decision"/>
    </action>

	<decision name="LkWIRMSetReq-Ingest-SPTT-Decision">
    	<switch>
			<case to="LkWIRMSetReq-Ingest-SPTT">${ wf:conf('job_TOULOUSE_OWNER_LkWIRMSetReq_DoFull') eq 'true'}</case>
            <default to="MachineStageType-Ingest-SPTT-Decision"/>
        </switch>
    </decision>

    <action name="LkWIRMSetReq-Ingest-SPTT">
        <sqoop xmlns="uri:oozie:sqoop-action:0.2">
			<job-tracker>${jobTracker}</job-tracker>
            <name-node>${nameNode}</name-node>
			<prepare>
            	<delete path="${job_TOULOUSE_OWNER_LkWIRMSetReq_DoFullTarget}" />
            </prepare>         	
            <arg>import</arg>
         	<arg>--connect</arg>
            <arg>jdbc:sqlserver://172.23.236.90:1433;database=TOULOUSE_OWNER</arg>
            <arg>--username</arg>
            <arg>usrSqoop</arg>
            <arg>--password</arg>
            <arg>AXm6Sn6#o</arg>
            <arg>--query</arg>
            <arg>SELECT LkWIRMSetReqID,WorkInstructionResultID,MeasurementSetRequiredID, 4 as "org_id",  'SPTT' as "org_name"   FROM dbo.LkWIRMSetReq WHERE ( $CONDITIONS ) </arg>
            <arg>--num-mappers</arg>
            <arg>1</arg>
            <arg>--target-dir</arg>
            <arg>${job_TOULOUSE_OWNER_LkWIRMSetReq_DoFullTarget}</arg>
            <arg>--fields-terminated-by</arg>
            <arg>\t</arg>
            <arg>--direct</arg>
            <arg>--</arg>
            <arg>--schema</arg>
            <arg>dbo</arg>
            <arg>-validate</arg>
        </sqoop>
        <ok to="MachineStageType-Ingest-SPTT-Decision"/>
        <error to="MachineStageType-Ingest-SPTT-Decision"/>
    </action>

	<decision name="MachineStageType-Ingest-SPTT-Decision">
    	<switch>
			<case to="MachineStageType-Ingest-SPTT">${ wf:conf('job_TOULOUSE_OWNER_MachineStageType_DoFull') eq 'true'}</case>
            <default to="MaintenancePartPlanned-Ingest-SPTT-Decision"/>
        </switch>
    </decision>

    <action name="MachineStageType-Ingest-SPTT">
        <sqoop xmlns="uri:oozie:sqoop-action:0.2">
			<job-tracker>${jobTracker}</job-tracker>
            <name-node>${nameNode}</name-node>
			<prepare>
            	<delete path="${job_TOULOUSE_OWNER_MachineStageType_DoFullTarget}" />
            </prepare>         	
            <arg>import</arg>
         	<arg>--connect</arg>
            <arg>jdbc:sqlserver://172.23.236.90:1433;database=TOULOUSE_OWNER</arg>
            <arg>--username</arg>
            <arg>usrSqoop</arg>
            <arg>--password</arg>
            <arg>AXm6Sn6#o</arg>
            <arg>--query</arg>
            <arg>SELECT MachineStageTypeID,Name,Description,MachineStageTypeCode, 4 as "org_id",  'SPTT' as "org_name"   FROM dbo.MachineStageType WHERE ( $CONDITIONS ) </arg>
            <arg>--num-mappers</arg>
            <arg>1</arg>
            <arg>--target-dir</arg>
            <arg>${job_TOULOUSE_OWNER_MachineStageType_DoFullTarget}</arg>
            <arg>--fields-terminated-by</arg>
            <arg>\t</arg>
            <arg>--direct</arg>
            <arg>--</arg>
            <arg>--schema</arg>
            <arg>dbo</arg>
            <arg>-validate</arg>
        </sqoop>
        <ok to="MaintenancePartPlanned-Ingest-SPTT-Decision"/>
        <error to="MaintenancePartPlanned-Ingest-SPTT-Decision"/>
    </action>

	<decision name="MaintenancePartPlanned-Ingest-SPTT-Decision">
    	<switch>
			<case to="MaintenancePartPlanned-Ingest-SPTT">${ wf:conf('job_TOULOUSE_OWNER_MaintenancePartPlanned_DoFull') eq 'true'}</case>
            <default to="MaintenanceProcedureStep-Ingest-SPTT-Decision"/>
        </switch>
    </decision>

    <action name="MaintenancePartPlanned-Ingest-SPTT">
        <sqoop xmlns="uri:oozie:sqoop-action:0.2">
			<job-tracker>${jobTracker}</job-tracker>
            <name-node>${nameNode}</name-node>
			<prepare>
            	<delete path="${job_TOULOUSE_OWNER_MaintenancePartPlanned_DoFullTarget}" />
            </prepare>         	
            <arg>import</arg>
         	<arg>--connect</arg>
            <arg>jdbc:sqlserver://172.23.236.90:1433;database=TOULOUSE_OWNER</arg>
            <arg>--username</arg>
            <arg>usrSqoop</arg>
            <arg>--password</arg>
            <arg>AXm6Sn6#o</arg>
            <arg>--query</arg>
            <arg>SELECT MaintenancePartPlannedID,MaintenanceProcedureStepID,PartID,PlannedCost,IsOptional,Quantity,UnitID, 4 as "org_id",  'SPTT' as "org_name"   FROM dbo.MaintenancePartPlanned WHERE ( $CONDITIONS ) </arg>
            <arg>--num-mappers</arg>
            <arg>1</arg>
            <arg>--target-dir</arg>
            <arg>${job_TOULOUSE_OWNER_MaintenancePartPlanned_DoFullTarget}</arg>
            <arg>--fields-terminated-by</arg>
            <arg>\t</arg>
            <arg>--direct</arg>
            <arg>--</arg>
            <arg>--schema</arg>
            <arg>dbo</arg>
            <arg>-validate</arg>
        </sqoop>
        <ok to="MaintenanceProcedureStep-Ingest-SPTT-Decision"/>
        <error to="MaintenanceProcedureStep-Ingest-SPTT-Decision"/>
    </action>

	<decision name="MaintenanceProcedureStep-Ingest-SPTT-Decision">
    	<switch>
			<case to="MaintenanceProcedureStep-Ingest-SPTT">${ wf:conf('job_TOULOUSE_OWNER_MaintenanceProcedureStep_DoFull') eq 'true'}</case>
            <default to="MeasurementSetP-Ingest-SPTT-Decision"/>
        </switch>
    </decision>

    <action name="MaintenanceProcedureStep-Ingest-SPTT">
        <sqoop xmlns="uri:oozie:sqoop-action:0.2">
			<job-tracker>${jobTracker}</job-tracker>
            <name-node>${nameNode}</name-node>
			<prepare>
            	<delete path="${job_TOULOUSE_OWNER_MaintenanceProcedureStep_DoFullTarget}" />
            </prepare>         	
            <arg>import</arg>
         	<arg>--connect</arg>
            <arg>jdbc:sqlserver://172.23.236.90:1433;database=TOULOUSE_OWNER</arg>
            <arg>--username</arg>
            <arg>usrSqoop</arg>
            <arg>--password</arg>
            <arg>AXm6Sn6#o</arg>
            <arg>--query</arg>
            <arg>SELECT MaintenanceProcedureStepID,MaintenanceProcedureStep,MaintenanceProcedureRevisionID,StepOrder,SubPartID,Component,RfMaintenanceCheckTypeID,RfSpecialActionTypeID,Test,USL,LSL,PersonnelGroupID,SupplierID,Nom,Units,DecPlaces, 4 as "org_id",  'SPTT' as "org_name"   FROM dbo.MaintenanceProcedureStep WHERE ( $CONDITIONS ) </arg>
            <arg>--num-mappers</arg>
            <arg>1</arg>
            <arg>--target-dir</arg>
            <arg>${job_TOULOUSE_OWNER_MaintenanceProcedureStep_DoFullTarget}</arg>
            <arg>--fields-terminated-by</arg>
            <arg>\t</arg>
            <arg>--direct</arg>
            <arg>--</arg>
            <arg>--schema</arg>
            <arg>dbo</arg>
            <arg>-validate</arg>
        </sqoop>
        <ok to="MeasurementSetP-Ingest-SPTT-Decision"/>
        <error to="MeasurementSetP-Ingest-SPTT-Decision"/>
    </action>

	<decision name="MeasurementSetP-Ingest-SPTT-Decision">
    	<switch>
			<case to="MeasurementSetP-Ingest-SPTT">${ wf:conf('job_TOULOUSE_OWNER_MeasurementSetP_DoFull') eq 'true'}</case>
            <default to="OPCCounter-Ingest-SPTT-Decision"/>
        </switch>
    </decision>

    <action name="MeasurementSetP-Ingest-SPTT">
        <sqoop xmlns="uri:oozie:sqoop-action:0.2">
			<job-tracker>${jobTracker}</job-tracker>
            <name-node>${nameNode}</name-node>
			<prepare>
            	<delete path="${job_TOULOUSE_OWNER_MeasurementSetP_DoFullTarget}" />
            </prepare>         	
            <arg>import</arg>
         	<arg>--connect</arg>
            <arg>jdbc:sqlserver://172.23.236.90:1433;database=TOULOUSE_OWNER</arg>
            <arg>--username</arg>
            <arg>usrSqoop</arg>
            <arg>--password</arg>
            <arg>AXm6Sn6#o</arg>
            <arg>--query</arg>
            <arg>SELECT MeasurementSetPID,ActualAttrSampleSize,AcquisitionContextID,IsEdited,DT,AcquisitionID,MachineStageID,RfAcquisitionClassID,RevisionNo,PartID,JobID, 4 as "org_id",  'SPTT' as "org_name"   FROM dbo.MeasurementSetP WHERE ( $CONDITIONS ) </arg>
            <arg>--num-mappers</arg>
            <arg>1</arg>
            <arg>--target-dir</arg>
            <arg>${job_TOULOUSE_OWNER_MeasurementSetP_DoFullTarget}</arg>
            <arg>--fields-terminated-by</arg>
            <arg>\t</arg>
            <arg>--direct</arg>
            <arg>--</arg>
            <arg>--schema</arg>
            <arg>dbo</arg>
            <arg>-validate</arg>
        </sqoop>
        <ok to="OPCCounter-Ingest-SPTT-Decision"/>
        <error to="OPCCounter-Ingest-SPTT-Decision"/>
    </action>

	<decision name="OPCCounter-Ingest-SPTT-Decision">
    	<switch>
			<case to="OPCCounter-Ingest-SPTT">${ wf:conf('job_TOULOUSE_OWNER_OPCCounter_DoFull') eq 'true'}</case>
            <default to="OPCMachineEventCode-Ingest-SPTT-Decision"/>
        </switch>
    </decision>

    <action name="OPCCounter-Ingest-SPTT">
        <sqoop xmlns="uri:oozie:sqoop-action:0.2">
			<job-tracker>${jobTracker}</job-tracker>
            <name-node>${nameNode}</name-node>
			<prepare>
            	<delete path="${job_TOULOUSE_OWNER_OPCCounter_DoFullTarget}" />
            </prepare>         	
            <arg>import</arg>
         	<arg>--connect</arg>
            <arg>jdbc:sqlserver://172.23.236.90:1433;database=TOULOUSE_OWNER</arg>
            <arg>--username</arg>
            <arg>usrSqoop</arg>
            <arg>--password</arg>
            <arg>AXm6Sn6#o</arg>
            <arg>--query</arg>
            <arg>SELECT OPCCounterID,OPCItemID,Description,LoValue,HiValue,Scale,Offset,Formula,UnitCountTypeID,ScrapReasonID,ModifiedDT,LoginID,IsProduction,AcceptableRateOfChange,RfDeltaValueModeID, 4 as "org_id",  'SPTT' as "org_name"   FROM dbo.OPCCounter WHERE ( $CONDITIONS ) </arg>
            <arg>--num-mappers</arg>
            <arg>1</arg>
            <arg>--target-dir</arg>
            <arg>${job_TOULOUSE_OWNER_OPCCounter_DoFullTarget}</arg>
            <arg>--fields-terminated-by</arg>
            <arg>\t</arg>
            <arg>--direct</arg>
            <arg>--</arg>
            <arg>--schema</arg>
            <arg>dbo</arg>
            <arg>-validate</arg>
        </sqoop>
        <ok to="OPCMachineEventCode-Ingest-SPTT-Decision"/>
        <error to="OPCMachineEventCode-Ingest-SPTT-Decision"/>
    </action>

	<decision name="OPCMachineEventCode-Ingest-SPTT-Decision">
    	<switch>
			<case to="OPCMachineEventCode-Ingest-SPTT">${ wf:conf('job_TOULOUSE_OWNER_OPCMachineEventCode_DoFull') eq 'true'}</case>
            <default to="OperationType-Ingest-SPTM-Decision"/>
        </switch>
    </decision>

    <action name="OPCMachineEventCode-Ingest-SPTT">
        <sqoop xmlns="uri:oozie:sqoop-action:0.2">
			<job-tracker>${jobTracker}</job-tracker>
            <name-node>${nameNode}</name-node>
			<prepare>
            	<delete path="${job_TOULOUSE_OWNER_OPCMachineEventCode_DoFullTarget}" />
            </prepare>         	
            <arg>import</arg>
         	<arg>--connect</arg>
            <arg>jdbc:sqlserver://172.23.236.90:1433;database=TOULOUSE_OWNER</arg>
            <arg>--username</arg>
            <arg>usrSqoop</arg>
            <arg>--password</arg>
            <arg>AXm6Sn6#o</arg>
            <arg>--query</arg>
            <arg>SELECT OPCMachineEventCodeID,OPCMachineEventCode,OPCMachineEventID,MachineStopReasonID,IsRunning, 4 as "org_id",  'SPTT' as "org_name"   FROM dbo.OPCMachineEventCode WHERE ( $CONDITIONS ) </arg>
            <arg>--num-mappers</arg>
            <arg>1</arg>
            <arg>--target-dir</arg>
            <arg>${job_TOULOUSE_OWNER_OPCMachineEventCode_DoFullTarget}</arg>
            <arg>--fields-terminated-by</arg>
            <arg>\t</arg>
            <arg>--direct</arg>
            <arg>--</arg>
            <arg>--schema</arg>
            <arg>dbo</arg>
            <arg>-validate</arg>
        </sqoop>
        <ok to="OperationType-Ingest-SPTM-Decision"/>
        <error to="OperationType-Ingest-SPTM-Decision"/>
    </action>

	<decision name="OperationType-Ingest-SPTM-Decision">
    	<switch>
			<case to="OperationType-Ingest-SPTM">${ wf:conf('job_CAPETOWN_OWNER_OperationType_DoFull') eq 'true'}</case>
            <default to="ProductionStop_-Ingest-SPTT-Decision"/>
        </switch>
    </decision>

    <action name="OperationType-Ingest-SPTM">
        <sqoop xmlns="uri:oozie:sqoop-action:0.2">
			<job-tracker>${jobTracker}</job-tracker>
            <name-node>${nameNode}</name-node>
			<prepare>
            	<delete path="${job_CAPETOWN_OWNER_OperationType_DoFullTarget}" />
            </prepare>         	
            <arg>import</arg>
         	<arg>--connect</arg>
            <arg>jdbc:sqlserver://172.23.236.90:1433;database=CAPETOWN_OWNER</arg>
            <arg>--username</arg>
            <arg>usrSqoop</arg>
            <arg>--password</arg>
            <arg>AXm6Sn6#o</arg>
            <arg>--query</arg>
            <arg>SELECT OperationTypeID,OperationType,OperationTypeCode,Description,PartTypeID,Sequence,IsOptional, 5 as "org_id",  'SPTM' as "org_name"   FROM dbo.OperationType WHERE ( $CONDITIONS ) </arg>
            <arg>--num-mappers</arg>
            <arg>1</arg>
            <arg>--target-dir</arg>
            <arg>${job_CAPETOWN_OWNER_OperationType_DoFullTarget}</arg>
            <arg>--fields-terminated-by</arg>
            <arg>\t</arg>
            <arg>--direct</arg>
            <arg>--</arg>
            <arg>--schema</arg>
            <arg>dbo</arg>
            <arg>-validate</arg>
        </sqoop>
        <ok to="ProductionStop_-Ingest-SPTT-Decision"/>
        <error to="ProductionStop_-Ingest-SPTT-Decision"/>
    </action>

	<decision name="ProductionStop_-Ingest-SPTT-Decision">
    	<switch>
			<case to="ProductionStop_-Ingest-SPTT">${ wf:conf('job_TOULOUSE_OWNER_ProductionStop__DoFull') eq 'true'}</case>
            <default to="Scrap_-Ingest-SPTT-Decision"/>
        </switch>
    </decision>

    <action name="ProductionStop_-Ingest-SPTT">
        <sqoop xmlns="uri:oozie:sqoop-action:0.2">
			<job-tracker>${jobTracker}</job-tracker>
            <name-node>${nameNode}</name-node>
			<prepare>
            	<delete path="${job_TOULOUSE_OWNER_ProductionStop__DoFullTarget}" />
            </prepare>         	
            <arg>import</arg>
         	<arg>--connect</arg>
            <arg>jdbc:sqlserver://172.23.236.90:1433;database=TOULOUSE_OWNER</arg>
            <arg>--username</arg>
            <arg>usrSqoop</arg>
            <arg>--password</arg>
            <arg>AXm6Sn6#o</arg>
            <arg>--query</arg>
            <arg>SELECT ProductionStopID,StopComments,StopLoginID,OpenedStopDT,SavedStopDT,OriginalLoginID,EditedProductionStopID, 4 as "org_id",  'SPTT' as "org_name"   FROM dbo.ProductionStop_ WHERE ( $CONDITIONS ) </arg>
            <arg>--num-mappers</arg>
            <arg>1</arg>
            <arg>--target-dir</arg>
            <arg>${job_TOULOUSE_OWNER_ProductionStop__DoFullTarget}</arg>
            <arg>--fields-terminated-by</arg>
            <arg>\t</arg>
            <arg>--direct</arg>
            <arg>--</arg>
            <arg>--schema</arg>
            <arg>dbo</arg>
            <arg>-validate</arg>
        </sqoop>
        <ok to="Scrap_-Ingest-SPTT-Decision"/>
        <error to="Scrap_-Ingest-SPTT-Decision"/>
    </action>

	<decision name="Scrap_-Ingest-SPTT-Decision">
    	<switch>
			<case to="Scrap_-Ingest-SPTT">${ wf:conf('job_TOULOUSE_OWNER_Scrap__DoFull') eq 'true'}</case>
            <default to="Shift-Ingest-SPTT-Decision"/>
        </switch>
    </decision>

    <action name="Scrap_-Ingest-SPTT">
        <sqoop xmlns="uri:oozie:sqoop-action:0.2">
			<job-tracker>${jobTracker}</job-tracker>
            <name-node>${nameNode}</name-node>
			<prepare>
            	<delete path="${job_TOULOUSE_OWNER_Scrap__DoFullTarget}" />
            </prepare>         	
            <arg>import</arg>
         	<arg>--connect</arg>
            <arg>jdbc:sqlserver://172.23.236.90:1433;database=TOULOUSE_OWNER</arg>
            <arg>--username</arg>
            <arg>usrSqoop</arg>
            <arg>--password</arg>
            <arg>AXm6Sn6#o</arg>
            <arg>--query</arg>
            <arg>SELECT ScrapID,CollectionQuantity,CollectionUnitID,Comments,LoginID,OpenedDT,SavedDT,OriginalLoginID,EditedScrapID,Reference1,Reference2,Reference3,Reference4,Reference5, 4 as "org_id",  'SPTT' as "org_name"   FROM dbo.Scrap_ WHERE ( $CONDITIONS ) </arg>
            <arg>--num-mappers</arg>
            <arg>1</arg>
            <arg>--target-dir</arg>
            <arg>${job_TOULOUSE_OWNER_Scrap__DoFullTarget}</arg>
            <arg>--fields-terminated-by</arg>
            <arg>\t</arg>
            <arg>--direct</arg>
            <arg>--</arg>
            <arg>--schema</arg>
            <arg>dbo</arg>
            <arg>-validate</arg>
        </sqoop>
        <ok to="Shift-Ingest-SPTT-Decision"/>
        <error to="Shift-Ingest-SPTT-Decision"/>
    </action>

	<decision name="Shift-Ingest-SPTT-Decision">
    	<switch>
			<case to="Shift-Ingest-SPTT">${ wf:conf('job_TOULOUSE_OWNER_Shift_DoFull') eq 'true'}</case>
            <default to="SPCChartComponent-Ingest-SPTT-Decision"/>
        </switch>
    </decision>

    <action name="Shift-Ingest-SPTT">
        <sqoop xmlns="uri:oozie:sqoop-action:0.2">
			<job-tracker>${jobTracker}</job-tracker>
            <name-node>${nameNode}</name-node>
			<prepare>
            	<delete path="${job_TOULOUSE_OWNER_Shift_DoFullTarget}" />
            </prepare>         	
            <arg>import</arg>
         	<arg>--connect</arg>
            <arg>jdbc:sqlserver://172.23.236.90:1433;database=TOULOUSE_OWNER</arg>
            <arg>--username</arg>
            <arg>usrSqoop</arg>
            <arg>--password</arg>
            <arg>AXm6Sn6#o</arg>
            <arg>--query</arg>
            <arg>SELECT ShiftID,ShiftTypeID,ShiftPatternID,FromDT,ToDT,Sequence, 4 as "org_id",  'SPTT' as "org_name"   FROM dbo.Shift WHERE ( $CONDITIONS ) </arg>
            <arg>--num-mappers</arg>
            <arg>1</arg>
            <arg>--target-dir</arg>
            <arg>${job_TOULOUSE_OWNER_Shift_DoFullTarget}</arg>
            <arg>--fields-terminated-by</arg>
            <arg>\t</arg>
            <arg>--direct</arg>
            <arg>--</arg>
            <arg>--schema</arg>
            <arg>dbo</arg>
            <arg>-validate</arg>
        </sqoop>
        <ok to="SPCChartComponent-Ingest-SPTT-Decision"/>
        <error to="SPCChartComponent-Ingest-SPTT-Decision"/>
    </action>

	<decision name="SPCChartComponent-Ingest-SPTT-Decision">
    	<switch>
			<case to="SPCChartComponent-Ingest-SPTT">${ wf:conf('job_TOULOUSE_OWNER_SPCChartComponent_DoFull') eq 'true'}</case>
            <default to="SPCDefaultControlLimit-Ingest-SPTT-Decision"/>
        </switch>
    </decision>

    <action name="SPCChartComponent-Ingest-SPTT">
        <sqoop xmlns="uri:oozie:sqoop-action:0.2">
			<job-tracker>${jobTracker}</job-tracker>
            <name-node>${nameNode}</name-node>
			<prepare>
            	<delete path="${job_TOULOUSE_OWNER_SPCChartComponent_DoFullTarget}" />
            </prepare>         	
            <arg>import</arg>
         	<arg>--connect</arg>
            <arg>jdbc:sqlserver://172.23.236.90:1433;database=TOULOUSE_OWNER</arg>
            <arg>--username</arg>
            <arg>usrSqoop</arg>
            <arg>--password</arg>
            <arg>AXm6Sn6#o</arg>
            <arg>--query</arg>
            <arg>SELECT SPCChartComponentID,SPCChartDefID,SPCVarChartID, 4 as "org_id",  'SPTT' as "org_name"   FROM dbo.SPCChartComponent WHERE ( $CONDITIONS ) </arg>
            <arg>--num-mappers</arg>
            <arg>1</arg>
            <arg>--target-dir</arg>
            <arg>${job_TOULOUSE_OWNER_SPCChartComponent_DoFullTarget}</arg>
            <arg>--fields-terminated-by</arg>
            <arg>\t</arg>
            <arg>--direct</arg>
            <arg>--</arg>
            <arg>--schema</arg>
            <arg>dbo</arg>
            <arg>-validate</arg>
        </sqoop>
        <ok to="SPCDefaultControlLimit-Ingest-SPTT-Decision"/>
        <error to="SPCDefaultControlLimit-Ingest-SPTT-Decision"/>
    </action>

	<decision name="SPCDefaultControlLimit-Ingest-SPTT-Decision">
    	<switch>
			<case to="SPCDefaultControlLimit-Ingest-SPTT">${ wf:conf('job_TOULOUSE_OWNER_SPCDefaultControlLimit_DoFull') eq 'true'}</case>
            <default to="TagCauseAction-Ingest-SPTT-Decision"/>
        </switch>
    </decision>

    <action name="SPCDefaultControlLimit-Ingest-SPTT">
        <sqoop xmlns="uri:oozie:sqoop-action:0.2">
			<job-tracker>${jobTracker}</job-tracker>
            <name-node>${nameNode}</name-node>
			<prepare>
            	<delete path="${job_TOULOUSE_OWNER_SPCDefaultControlLimit_DoFullTarget}" />
            </prepare>         	
            <arg>import</arg>
         	<arg>--connect</arg>
            <arg>jdbc:sqlserver://172.23.236.90:1433;database=TOULOUSE_OWNER</arg>
            <arg>--username</arg>
            <arg>usrSqoop</arg>
            <arg>--password</arg>
            <arg>AXm6Sn6#o</arg>
            <arg>--query</arg>
            <arg>SELECT SPCDefaultControlLimitID,SPCChartDefID,RfChartComponentID,RfChart,UCL,CL,LCL,ModifiedDT,LoginID,ProductID, 4 as "org_id",  'SPTT' as "org_name"   FROM dbo.SPCDefaultControlLimit WHERE ( $CONDITIONS ) </arg>
            <arg>--num-mappers</arg>
            <arg>1</arg>
            <arg>--target-dir</arg>
            <arg>${job_TOULOUSE_OWNER_SPCDefaultControlLimit_DoFullTarget}</arg>
            <arg>--fields-terminated-by</arg>
            <arg>\t</arg>
            <arg>--direct</arg>
            <arg>--</arg>
            <arg>--schema</arg>
            <arg>dbo</arg>
            <arg>-validate</arg>
        </sqoop>
        <ok to="TagCauseAction-Ingest-SPTT-Decision"/>
        <error to="TagCauseAction-Ingest-SPTT-Decision"/>
    </action>

	<decision name="TagCauseAction-Ingest-SPTT-Decision">
    	<switch>
			<case to="TagCauseAction-Ingest-SPTT">${ wf:conf('job_TOULOUSE_OWNER_TagCauseAction_DoFull') eq 'true'}</case>
            <default to="TagTree-Ingest-SPTT-Decision"/>
        </switch>
    </decision>

    <action name="TagCauseAction-Ingest-SPTT">
        <sqoop xmlns="uri:oozie:sqoop-action:0.2">
			<job-tracker>${jobTracker}</job-tracker>
            <name-node>${nameNode}</name-node>
			<prepare>
            	<delete path="${job_TOULOUSE_OWNER_TagCauseAction_DoFullTarget}" />
            </prepare>         	
            <arg>import</arg>
         	<arg>--connect</arg>
            <arg>jdbc:sqlserver://172.23.236.90:1433;database=TOULOUSE_OWNER</arg>
            <arg>--username</arg>
            <arg>usrSqoop</arg>
            <arg>--password</arg>
            <arg>AXm6Sn6#o</arg>
            <arg>--query</arg>
            <arg>SELECT TagCauseActionID,CauseActionID,TagTypeID,TagValue,DT, 4 as "org_id",  'SPTT' as "org_name"   FROM dbo.TagCauseAction WHERE ( $CONDITIONS ) </arg>
            <arg>--num-mappers</arg>
            <arg>1</arg>
            <arg>--target-dir</arg>
            <arg>${job_TOULOUSE_OWNER_TagCauseAction_DoFullTarget}</arg>
            <arg>--fields-terminated-by</arg>
            <arg>\t</arg>
            <arg>--direct</arg>
            <arg>--</arg>
            <arg>--schema</arg>
            <arg>dbo</arg>
            <arg>-validate</arg>
        </sqoop>
        <ok to="TagTree-Ingest-SPTT-Decision"/>
        <error to="TagTree-Ingest-SPTT-Decision"/>
    </action>

	<decision name="TagTree-Ingest-SPTT-Decision">
    	<switch>
			<case to="TagTree-Ingest-SPTT">${ wf:conf('job_TOULOUSE_OWNER_TagTree_DoFull') eq 'true'}</case>
            <default to="TMP_Job_Shift_Downtime-Ingest-SPTT-Decision"/>
        </switch>
    </decision>

    <action name="TagTree-Ingest-SPTT">
        <sqoop xmlns="uri:oozie:sqoop-action:0.2">
			<job-tracker>${jobTracker}</job-tracker>
            <name-node>${nameNode}</name-node>
			<prepare>
            	<delete path="${job_TOULOUSE_OWNER_TagTree_DoFullTarget}" />
            </prepare>         	
            <arg>import</arg>
         	<arg>--connect</arg>
            <arg>jdbc:sqlserver://172.23.236.90:1433;database=TOULOUSE_OWNER</arg>
            <arg>--username</arg>
            <arg>usrSqoop</arg>
            <arg>--password</arg>
            <arg>AXm6Sn6#o</arg>
            <arg>--query</arg>
            <arg>SELECT TagTreeID,TagTree, 4 as "org_id",  'SPTT' as "org_name"   FROM dbo.TagTree WHERE ( $CONDITIONS ) </arg>
            <arg>--num-mappers</arg>
            <arg>1</arg>
            <arg>--target-dir</arg>
            <arg>${job_TOULOUSE_OWNER_TagTree_DoFullTarget}</arg>
            <arg>--fields-terminated-by</arg>
            <arg>\t</arg>
            <arg>--direct</arg>
            <arg>--</arg>
            <arg>--schema</arg>
            <arg>dbo</arg>
            <arg>-validate</arg>
        </sqoop>
        <ok to="TMP_Job_Shift_Downtime-Ingest-SPTT-Decision"/>
        <error to="TMP_Job_Shift_Downtime-Ingest-SPTT-Decision"/>
    </action>

	<decision name="TMP_Job_Shift_Downtime-Ingest-SPTT-Decision">
    	<switch>
			<case to="TMP_Job_Shift_Downtime-Ingest-SPTT">${ wf:conf('job_TOULOUSE_OWNER_TMP_Job_Shift_Downtime_DoFull') eq 'true'}</case>
            <default to="ToolCavity-Ingest-SPTT-Decision"/>
        </switch>
    </decision>

    <action name="TMP_Job_Shift_Downtime-Ingest-SPTT">
        <sqoop xmlns="uri:oozie:sqoop-action:0.2">
			<job-tracker>${jobTracker}</job-tracker>
            <name-node>${nameNode}</name-node>
			<prepare>
            	<delete path="${job_TOULOUSE_OWNER_TMP_Job_Shift_Downtime_DoFullTarget}" />
            </prepare>         	
            <arg>import</arg>
         	<arg>--connect</arg>
            <arg>jdbc:sqlserver://172.23.236.90:1433;database=TOULOUSE_OWNER</arg>
            <arg>--username</arg>
            <arg>usrSqoop</arg>
            <arg>--password</arg>
            <arg>AXm6Sn6#o</arg>
            <arg>--query</arg>
            <arg>SELECT ShiftID,MachineStageID,JobID,Downtime, 4 as "org_id",  'SPTT' as "org_name"   FROM dbo.TMP_Job_Shift_Downtime WHERE ( $CONDITIONS ) </arg>
            <arg>--num-mappers</arg>
            <arg>1</arg>
            <arg>--target-dir</arg>
            <arg>${job_TOULOUSE_OWNER_TMP_Job_Shift_Downtime_DoFullTarget}</arg>
            <arg>--fields-terminated-by</arg>
            <arg>\t</arg>
            <arg>--direct</arg>
            <arg>--</arg>
            <arg>--schema</arg>
            <arg>dbo</arg>
            <arg>-validate</arg>
        </sqoop>
        <ok to="ToolCavity-Ingest-SPTT-Decision"/>
        <error to="ToolCavity-Ingest-SPTT-Decision"/>
    </action>

	<decision name="ToolCavity-Ingest-SPTT-Decision">
    	<switch>
			<case to="ToolCavity-Ingest-SPTT">${ wf:conf('job_TOULOUSE_OWNER_ToolCavity_DoFull') eq 'true'}</case>
            <default to="ToolUsage-Ingest-SPTT-Decision"/>
        </switch>
    </decision>

    <action name="ToolCavity-Ingest-SPTT">
        <sqoop xmlns="uri:oozie:sqoop-action:0.2">
			<job-tracker>${jobTracker}</job-tracker>
            <name-node>${nameNode}</name-node>
			<prepare>
            	<delete path="${job_TOULOUSE_OWNER_ToolCavity_DoFullTarget}" />
            </prepare>         	
            <arg>import</arg>
         	<arg>--connect</arg>
            <arg>jdbc:sqlserver://172.23.236.90:1433;database=TOULOUSE_OWNER</arg>
            <arg>--username</arg>
            <arg>usrSqoop</arg>
            <arg>--password</arg>
            <arg>AXm6Sn6#o</arg>
            <arg>--query</arg>
            <arg>SELECT ToolCavityID,CavityNumber,CavityName,ToolID, 4 as "org_id",  'SPTT' as "org_name"   FROM dbo.ToolCavity WHERE ( $CONDITIONS ) </arg>
            <arg>--num-mappers</arg>
            <arg>1</arg>
            <arg>--target-dir</arg>
            <arg>${job_TOULOUSE_OWNER_ToolCavity_DoFullTarget}</arg>
            <arg>--fields-terminated-by</arg>
            <arg>\t</arg>
            <arg>--direct</arg>
            <arg>--</arg>
            <arg>--schema</arg>
            <arg>dbo</arg>
            <arg>-validate</arg>
        </sqoop>
        <ok to="ToolUsage-Ingest-SPTT-Decision"/>
        <error to="ToolUsage-Ingest-SPTT-Decision"/>
    </action>

	<decision name="ToolUsage-Ingest-SPTT-Decision">
    	<switch>
			<case to="ToolUsage-Ingest-SPTT">${ wf:conf('job_TOULOUSE_OWNER_ToolUsage_DoFull') eq 'true'}</case>
            <default to="VarChartOC-Ingest-SPTT-Decision"/>
        </switch>
    </decision>

    <action name="ToolUsage-Ingest-SPTT">
        <sqoop xmlns="uri:oozie:sqoop-action:0.2">
			<job-tracker>${jobTracker}</job-tracker>
            <name-node>${nameNode}</name-node>
			<prepare>
            	<delete path="${job_TOULOUSE_OWNER_ToolUsage_DoFullTarget}" />
            </prepare>         	
            <arg>import</arg>
         	<arg>--connect</arg>
            <arg>jdbc:sqlserver://172.23.236.90:1433;database=TOULOUSE_OWNER</arg>
            <arg>--username</arg>
            <arg>usrSqoop</arg>
            <arg>--password</arg>
            <arg>AXm6Sn6#o</arg>
            <arg>--query</arg>
            <arg>SELECT ToolUsageID,JobID,MachineStageID,ToolID,FromDT,ToDT,ToolPosition,ToolChangeReasonID,IsEdited,RevisionNo,OperationID, 4 as "org_id",  'SPTT' as "org_name"   FROM dbo.ToolUsage WHERE ( $CONDITIONS ) </arg>
            <arg>--num-mappers</arg>
            <arg>1</arg>
            <arg>--target-dir</arg>
            <arg>${job_TOULOUSE_OWNER_ToolUsage_DoFullTarget}</arg>
            <arg>--fields-terminated-by</arg>
            <arg>\t</arg>
            <arg>--direct</arg>
            <arg>--</arg>
            <arg>--schema</arg>
            <arg>dbo</arg>
            <arg>-validate</arg>
        </sqoop>
        <ok to="VarChartOC-Ingest-SPTT-Decision"/>
        <error to="VarChartOC-Ingest-SPTT-Decision"/>
    </action>

	<decision name="VarChartOC-Ingest-SPTT-Decision">
    	<switch>
			<case to="VarChartOC-Ingest-SPTT">${ wf:conf('job_TOULOUSE_OWNER_VarChartOC_DoFull') eq 'true'}</case>
            <default to="WO_-Ingest-SPTT-Decision"/>
        </switch>
    </decision>

    <action name="VarChartOC-Ingest-SPTT">
        <sqoop xmlns="uri:oozie:sqoop-action:0.2">
			<job-tracker>${jobTracker}</job-tracker>
            <name-node>${nameNode}</name-node>
			<prepare>
            	<delete path="${job_TOULOUSE_OWNER_VarChartOC_DoFullTarget}" />
            </prepare>         	
            <arg>import</arg>
         	<arg>--connect</arg>
            <arg>jdbc:sqlserver://172.23.236.90:1433;database=TOULOUSE_OWNER</arg>
            <arg>--username</arg>
            <arg>usrSqoop</arg>
            <arg>--password</arg>
            <arg>AXm6Sn6#o</arg>
            <arg>--query</arg>
            <arg>SELECT VarChartOCID,MeasurementSetID,SPCChartControlLimitID,SubgroupID, 4 as "org_id",  'SPTT' as "org_name"   FROM dbo.VarChartOC WHERE ( $CONDITIONS ) </arg>
            <arg>--num-mappers</arg>
            <arg>1</arg>
            <arg>--target-dir</arg>
            <arg>${job_TOULOUSE_OWNER_VarChartOC_DoFullTarget}</arg>
            <arg>--fields-terminated-by</arg>
            <arg>\t</arg>
            <arg>--direct</arg>
            <arg>--</arg>
            <arg>--schema</arg>
            <arg>dbo</arg>
            <arg>-validate</arg>
        </sqoop>
        <ok to="WO_-Ingest-SPTT-Decision"/>
        <error to="WO_-Ingest-SPTT-Decision"/>
    </action>

	<decision name="WO_-Ingest-SPTT-Decision">
    	<switch>
			<case to="WO_-Ingest-SPTT">${ wf:conf('job_TOULOUSE_OWNER_WO__DoFull') eq 'true'}</case>
            <default to="Job-Ingest-SPTM-Decision"/>
        </switch>
    </decision>

    <action name="WO_-Ingest-SPTT">
        <sqoop xmlns="uri:oozie:sqoop-action:0.2">
			<job-tracker>${jobTracker}</job-tracker>
            <name-node>${nameNode}</name-node>
			<prepare>
            	<delete path="${job_TOULOUSE_OWNER_WO__DoFullTarget}" />
            </prepare>         	
            <arg>import</arg>
         	<arg>--connect</arg>
            <arg>jdbc:sqlserver://172.23.236.90:1433;database=TOULOUSE_OWNER</arg>
            <arg>--username</arg>
            <arg>usrSqoop</arg>
            <arg>--password</arg>
            <arg>AXm6Sn6#o</arg>
            <arg>--query</arg>
            <arg>SELECT WOID,CustomerOrderNo,LabelsPerInventoryPack,ItemsPerInventoryPack,ItemsPerLayer,LayersPerInventoryPack,PackingCode,LabelTemplate,LabelColour,EANCode,CusStartNum,CusEndNum,CustomerPartNo,CustomerPartDescription,LabelText1,LabelText2,LabelText3,PrinterURL,BOMVariantID, 4 as "org_id",  'SPTT' as "org_name"   FROM dbo.WO_ WHERE ( $CONDITIONS ) </arg>
            <arg>--num-mappers</arg>
            <arg>1</arg>
            <arg>--target-dir</arg>
            <arg>${job_TOULOUSE_OWNER_WO__DoFullTarget}</arg>
            <arg>--fields-terminated-by</arg>
            <arg>\t</arg>
            <arg>--direct</arg>
            <arg>--</arg>
            <arg>--schema</arg>
            <arg>dbo</arg>
            <arg>-validate</arg>
        </sqoop>
        <ok to="Job-Ingest-SPTM-Decision"/>
        <error to="Job-Ingest-SPTM-Decision"/>
    </action>

	<decision name="Job-Ingest-SPTM-Decision">
    	<switch>
			<case to="Job-Ingest-SPTM">${ wf:conf('job_CAPETOWN_OWNER_Job_DoFull') eq 'true'}</case>
            <default to="End-Full-25-Ingest-Decision"/>
        </switch>
    </decision>

    <action name="Job-Ingest-SPTM">
        <sqoop xmlns="uri:oozie:sqoop-action:0.2">
			<job-tracker>${jobTracker}</job-tracker>
            <name-node>${nameNode}</name-node>
			<prepare>
            	<delete path="${job_CAPETOWN_OWNER_Job_DoFullTarget}" />
            </prepare>         	
            <arg>import</arg>
         	<arg>--connect</arg>
            <arg>jdbc:sqlserver://172.23.236.90:1433;database=CAPETOWN_OWNER</arg>
            <arg>--username</arg>
            <arg>usrSqoop</arg>
            <arg>--password</arg>
            <arg>AXm6Sn6#o</arg>
            <arg>--query</arg>
            <arg>SELECT Job.JobID, Job.WOID, Job.RfJobStatusID, Job.DeadlineDT, Job.ActualStartDT, Job.ActualEndDT, Job.PlannedStartDT, Job.PlannedEndDT, Job.PlannedDuration, Job.EstimatedStartDT, Job.EstimatedEndDT, Job.EstimatedDuration, Job.ScheduledSequence, Job.LineID, Job.ProductionStartDT, Job.ProductionEndDT, Job.TheoreticalCycleTime, Job.BudgetChangeOver, Job.QuantityOrdered, Job.IsCalculated, Job.LineGroupID, Job_.JobInstructions, Job_.ReleaseDT, Job_.ReleaseLoginID, Job_.StartLoginID, Job_.EndLoginID, Job_.Comments, Job_.ModifiedDt, Job_.ModifiedLoginID, Job_.StoppedReason, Job_.SkippedReason, Job_.SkippedDT,  5 as "org_id",  'SPTM' as "org_name"  FROM Job FULL JOIN Job_ ON (Job.JobID = Job_.JobID) FULL JOIN Job_Custom ON (Job.JobID = Job_Custom.JobID)   WHERE ( $CONDITIONS ) </arg>
            <arg>--num-mappers</arg>
            <arg>1</arg>
            <arg>--target-dir</arg>
            <arg>${job_CAPETOWN_OWNER_Job_DoFullTarget}</arg>
            <arg>--fields-terminated-by</arg>
            <arg>\t</arg>
            <arg>--direct</arg>
            <arg>--</arg>
            <arg>--schema</arg>
            <arg>dbo</arg>
            <arg>-validate</arg>
        </sqoop>
        <ok to="End-Full-25-Ingest-Decision"/>
        <error to="End-Full-25-Ingest-Decision"/>
    </action>

	<end name="End-Full-25-Ingest-Decision"/>
</workflow-app>
